{
	"token_matching": "minimal",
	"teacher_files": {
		"reconstructed.html": [
			{
				"token": "/",
				"label": "comment",
				"start": 529,
				"end": 530
			},
			{
				"token": "/",
				"label": "comment",
				"start": 530,
				"end": 531
			},
			{
				"token": "never",
				"label": "comment",
				"start": 532,
				"end": 537
			},
			{
				"token": "define",
				"label": "comment",
				"start": 538,
				"end": 544
			},
			{
				"token": "without",
				"label": "comment",
				"start": 545,
				"end": 552
			},
			{
				"token": "const",
				"label": "comment",
				"start": 553,
				"end": 558
			},
			{
				"token": ",",
				"label": "comment",
				"start": 558,
				"end": 559
			},
			{
				"token": "let",
				"label": "comment",
				"start": 560,
				"end": 563
			},
			{
				"token": "(",
				"label": "comment",
				"start": 564,
				"end": 565
			},
			{
				"token": "or",
				"label": "comment",
				"start": 565,
				"end": 567
			},
			{
				"token": "var",
				"label": "comment",
				"start": 568,
				"end": 571
			},
			{
				"token": ")",
				"label": "comment",
				"start": 571,
				"end": 572
			},
			{
				"token": "/",
				"label": "comment",
				"start": 733,
				"end": 734
			},
			{
				"token": "/",
				"label": "comment",
				"start": 734,
				"end": 735
			},
			{
				"token": "var",
				"label": "comment",
				"start": 736,
				"end": 739
			},
			{
				"token": "was",
				"label": "comment",
				"start": 740,
				"end": 743
			},
			{
				"token": "\"",
				"label": "comment",
				"start": 744,
				"end": 745
			},
			{
				"token": "replaced",
				"label": "comment",
				"start": 745,
				"end": 753
			},
			{
				"token": "\"",
				"label": "comment",
				"start": 753,
				"end": 754
			},
			{
				"token": "by",
				"label": "comment",
				"start": 755,
				"end": 757
			},
			{
				"token": "let",
				"label": "comment",
				"start": 758,
				"end": 761
			},
			{
				"token": "and",
				"label": "comment",
				"start": 762,
				"end": 765
			},
			{
				"token": "const",
				"label": "comment",
				"start": 766,
				"end": 771
			},
			{
				"token": "/",
				"label": "comment",
				"start": 816,
				"end": 817
			},
			{
				"token": "/",
				"label": "comment",
				"start": 817,
				"end": 818
			},
			{
				"token": "accepts",
				"label": "comment",
				"start": 819,
				"end": 826
			},
			{
				"token": "multiple",
				"label": "comment",
				"start": 827,
				"end": 835
			},
			{
				"token": "parameters",
				"label": "comment",
				"start": 836,
				"end": 846
			},
			{
				"token": "/",
				"label": "comment",
				"start": 1023,
				"end": 1024
			},
			{
				"token": "/",
				"label": "comment",
				"start": 1024,
				"end": 1025
			},
			{
				"token": "zero",
				"label": "comment",
				"start": 1026,
				"end": 1030
			},
			{
				"token": "is",
				"label": "comment",
				"start": 1031,
				"end": 1033
			},
			{
				"token": "\"",
				"label": "comment",
				"start": 1034,
				"end": 1035
			},
			{
				"token": "falsy",
				"label": "comment",
				"start": 1035,
				"end": 1040
			},
			{
				"token": "\"",
				"label": "comment",
				"start": 1040,
				"end": 1041
			},
			{
				"token": "/",
				"label": "comment",
				"start": 1049,
				"end": 1050
			},
			{
				"token": "/",
				"label": "comment",
				"start": 1050,
				"end": 1051
			},
			{
				"token": "arrays",
				"label": "comment",
				"start": 1052,
				"end": 1058
			},
			{
				"token": "are",
				"label": "comment",
				"start": 1059,
				"end": 1062
			},
			{
				"token": "like",
				"label": "comment",
				"start": 1063,
				"end": 1067
			},
			{
				"token": "Python",
				"label": "comment",
				"start": 1068,
				"end": 1074
			},
			{
				"token": "lists",
				"label": "comment",
				"start": 1075,
				"end": 1080
			},
			{
				"token": "/",
				"label": "comment",
				"start": 1217,
				"end": 1218
			},
			{
				"token": "/",
				"label": "comment",
				"start": 1218,
				"end": 1219
			},
			{
				"token": "myArray",
				"label": "comment",
				"start": 1220,
				"end": 1227
			},
			{
				"token": "=",
				"label": "comment",
				"start": 1228,
				"end": 1229
			},
			{
				"token": "[",
				"label": "comment",
				"start": 1230,
				"end": 1231
			},
			{
				"token": "1",
				"label": "comment",
				"start": 1231,
				"end": 1232
			},
			{
				"token": ",",
				"label": "comment",
				"start": 1232,
				"end": 1233
			},
			{
				"token": "2",
				"label": "comment",
				"start": 1234,
				"end": 1235
			},
			{
				"token": ",",
				"label": "comment",
				"start": 1235,
				"end": 1236
			},
			{
				"token": "3",
				"label": "comment",
				"start": 1237,
				"end": 1238
			},
			{
				"token": "]",
				"label": "comment",
				"start": 1238,
				"end": 1239
			},
			{
				"token": ";",
				"label": "comment",
				"start": 1239,
				"end": 1240
			},
			{
				"token": "ERROR",
				"label": "comment",
				"start": 1241,
				"end": 1246
			},
			{
				"token": "!",
				"label": "comment",
				"start": 1246,
				"end": 1247
			},
			{
				"token": "Program",
				"label": "comment",
				"start": 1248,
				"end": 1255
			},
			{
				"token": "would",
				"label": "comment",
				"start": 1256,
				"end": 1261
			},
			{
				"token": "fail",
				"label": "comment",
				"start": 1262,
				"end": 1266
			},
			{
				"token": "here",
				"label": "comment",
				"start": 1267,
				"end": 1271
			},
			{
				"token": "!",
				"label": "comment",
				"start": 1271,
				"end": 1272
			},
			{
				"token": "error",
				"label": "missing",
				"start": 1337,
				"end": 1342,
				"insert_at": {
					"file": "123456.html",
					"pos": 1510
				},
				"timestamp": "12:53:23"
			},
			{
				"token": "/",
				"label": "comment",
				"start": 1477,
				"end": 1478
			},
			{
				"token": "/",
				"label": "comment",
				"start": 1478,
				"end": 1479
			},
			{
				"token": "objects",
				"label": "comment",
				"start": 1480,
				"end": 1487
			},
			{
				"token": "are",
				"label": "comment",
				"start": 1488,
				"end": 1491
			},
			{
				"token": "like",
				"label": "comment",
				"start": 1492,
				"end": 1496
			},
			{
				"token": "Python",
				"label": "comment",
				"start": 1497,
				"end": 1503
			},
			{
				"token": "dictionaries",
				"label": "comment",
				"start": 1504,
				"end": 1516
			},
			{
				"token": "/",
				"label": "comment",
				"start": 1916,
				"end": 1917
			},
			{
				"token": "*",
				"label": "comment",
				"start": 1917,
				"end": 1918
			},
			{
				"token": "no",
				"label": "comment",
				"start": 1923,
				"end": 1925
			},
			{
				"token": "need",
				"label": "comment",
				"start": 1926,
				"end": 1930
			},
			{
				"token": "for",
				"label": "comment",
				"start": 1931,
				"end": 1934
			},
			{
				"token": "document",
				"label": "comment",
				"start": 1935,
				"end": 1943
			},
			{
				"token": ".",
				"label": "comment",
				"start": 1943,
				"end": 1944
			},
			{
				"token": "getElementById",
				"label": "comment",
				"start": 1944,
				"end": 1958
			},
			{
				"token": "(",
				"label": "comment",
				"start": 1958,
				"end": 1959
			},
			{
				"token": "\"",
				"label": "comment",
				"start": 1959,
				"end": 1960
			},
			{
				"token": "container",
				"label": "comment",
				"start": 1960,
				"end": 1969
			},
			{
				"token": "\"",
				"label": "comment",
				"start": 1969,
				"end": 1970
			},
			{
				"token": ")",
				"label": "comment",
				"start": 1970,
				"end": 1971
			},
			{
				"token": "ids",
				"label": "comment",
				"start": 1976,
				"end": 1979
			},
			{
				"token": "that",
				"label": "comment",
				"start": 1980,
				"end": 1984
			},
			{
				"token": "are",
				"label": "comment",
				"start": 1985,
				"end": 1988
			},
			{
				"token": "valid",
				"label": "comment",
				"start": 1989,
				"end": 1994
			},
			{
				"token": "JS",
				"label": "comment",
				"start": 1995,
				"end": 1997
			},
			{
				"token": "names",
				"label": "comment",
				"start": 1998,
				"end": 2003
			},
			{
				"token": "are",
				"label": "comment",
				"start": 2004,
				"end": 2007
			},
			{
				"token": "automatically",
				"label": "comment",
				"start": 2008,
				"end": 2021
			},
			{
				"token": "global",
				"label": "comment",
				"start": 2022,
				"end": 2028
			},
			{
				"token": "variables",
				"label": "comment",
				"start": 2029,
				"end": 2038
			},
			{
				"token": "invalid",
				"label": "comment",
				"start": 2043,
				"end": 2050
			},
			{
				"token": "names",
				"label": "comment",
				"start": 2051,
				"end": 2056
			},
			{
				"token": ":",
				"label": "comment",
				"start": 2056,
				"end": 2057
			},
			{
				"token": "*",
				"label": "comment",
				"start": 2063,
				"end": 2064
			},
			{
				"token": "start",
				"label": "comment",
				"start": 2065,
				"end": 2070
			},
			{
				"token": "with",
				"label": "comment",
				"start": 2071,
				"end": 2075
			},
			{
				"token": "a",
				"label": "comment",
				"start": 2076,
				"end": 2077
			},
			{
				"token": "number",
				"label": "comment",
				"start": 2078,
				"end": 2084
			},
			{
				"token": "*",
				"label": "comment",
				"start": 2090,
				"end": 2091
			},
			{
				"token": "contain",
				"label": "comment",
				"start": 2092,
				"end": 2099
			},
			{
				"token": "spaces",
				"label": "comment",
				"start": 2100,
				"end": 2106
			},
			{
				"token": "or",
				"label": "comment",
				"start": 2107,
				"end": 2109
			},
			{
				"token": "special",
				"label": "comment",
				"start": 2110,
				"end": 2117
			},
			{
				"token": "characters",
				"label": "comment",
				"start": 2118,
				"end": 2128
			},
			{
				"token": "(",
				"label": "comment",
				"start": 2129,
				"end": 2130
			},
			{
				"token": "like",
				"label": "comment",
				"start": 2130,
				"end": 2134
			},
			{
				"token": "-",
				"label": "comment",
				"start": 2135,
				"end": 2136
			},
			{
				"token": ")",
				"label": "comment",
				"start": 2136,
				"end": 2137
			},
			{
				"token": "*",
				"label": "comment",
				"start": 2141,
				"end": 2142
			},
			{
				"token": "/",
				"label": "comment",
				"start": 2142,
				"end": 2143
			},
			{
				"token": "/",
				"label": "comment",
				"start": 2179,
				"end": 2180
			},
			{
				"token": "/",
				"label": "comment",
				"start": 2180,
				"end": 2181
			},
			{
				"token": "operators",
				"label": "comment",
				"start": 2182,
				"end": 2191
			},
			{
				"token": "/",
				"label": "comment",
				"start": 2250,
				"end": 2251
			},
			{
				"token": "/",
				"label": "comment",
				"start": 2251,
				"end": 2252
			},
			{
				"token": "concatenation",
				"label": "comment",
				"start": 2253,
				"end": 2266
			},
			{
				"token": "console",
				"label": "missing",
				"start": 2339,
				"end": 2346,
				"insert_at": {
					"file": "123456.html",
					"pos": 2696
				},
				"timestamp": "13:22:01.859"
			},
			{
				"token": ".",
				"label": "missing",
				"start": 2346,
				"end": 2347,
				"insert_at": {
					"file": "123456.html",
					"pos": 2696
				},
				"timestamp": "13:22:02.110"
			},
			{
				"token": "log",
				"label": "missing",
				"start": 2347,
				"end": 2350,
				"insert_at": {
					"file": "123456.html",
					"pos": 2696
				},
				"timestamp": "13:22:02.836"
			},
			{
				"token": "(",
				"label": "missing",
				"start": 2350,
				"end": 2351,
				"insert_at": {
					"file": "123456.html",
					"pos": 2696
				},
				"timestamp": "13:22:03.038"
			},
			{
				"token": "a",
				"label": "missing",
				"start": 2351,
				"end": 2352,
				"insert_at": {
					"file": "123456.html",
					"pos": 2696
				},
				"timestamp": "13:22:03.297"
			},
			{
				"token": "%",
				"label": "missing",
				"start": 2353,
				"end": 2354,
				"insert_at": {
					"file": "123456.html",
					"pos": 2696
				},
				"timestamp": "13:22:03.842"
			},
			{
				"token": "b",
				"label": "missing",
				"start": 2355,
				"end": 2356,
				"insert_at": {
					"file": "123456.html",
					"pos": 2696
				},
				"timestamp": "13:22:04.523"
			},
			{
				"token": ")",
				"label": "missing",
				"start": 2356,
				"end": 2357,
				"insert_at": {
					"file": "123456.html",
					"pos": 2696
				},
				"timestamp": "13:22:05.089"
			},
			{
				"token": ";",
				"label": "missing",
				"start": 2357,
				"end": 2358,
				"insert_at": {
					"file": "123456.html",
					"pos": 2696
				},
				"timestamp": "13:22:05.323"
			},
			{
				"token": "a",
				"label": "missing",
				"start": 2575,
				"end": 2576,
				"insert_at": {
					"file": "123456.html",
					"pos": 2952
				},
				"timestamp": "13:25:59.379"
			},
			{
				"token": "/",
				"label": "missing",
				"start": 2577,
				"end": 2578,
				"insert_at": {
					"file": "123456.html",
					"pos": 2952
				},
				"timestamp": "13:26:00.029"
			},
			{
				"token": "=",
				"label": "missing",
				"start": 2578,
				"end": 2579,
				"insert_at": {
					"file": "123456.html",
					"pos": 2952
				},
				"timestamp": "13:26:00.357"
			},
			{
				"token": "3",
				"label": "missing",
				"start": 2580,
				"end": 2581,
				"insert_at": {
					"file": "123456.html",
					"pos": 2952
				},
				"timestamp": "13:26:01.048"
			},
			{
				"token": ";",
				"label": "missing",
				"start": 2581,
				"end": 2582,
				"insert_at": {
					"file": "123456.html",
					"pos": 2952
				},
				"timestamp": "13:26:02.451"
			},
			{
				"token": "/",
				"label": "comment",
				"start": 2747,
				"end": 2748
			},
			{
				"token": "/",
				"label": "comment",
				"start": 2748,
				"end": 2749
			},
			{
				"token": "escaping",
				"label": "comment",
				"start": 2750,
				"end": 2758
			},
			{
				"token": "with",
				"label": "comment",
				"start": 2759,
				"end": 2763
			},
			{
				"token": "\\",
				"label": "comment",
				"start": 2764,
				"end": 2765
			},
			{
				"token": "/",
				"label": "comment",
				"start": 2904,
				"end": 2905
			},
			{
				"token": "/",
				"label": "comment",
				"start": 2905,
				"end": 2906
			},
			{
				"token": "template",
				"label": "comment",
				"start": 2907,
				"end": 2915
			},
			{
				"token": "literal",
				"label": "comment",
				"start": 2916,
				"end": 2923
			},
			{
				"token": "default",
				"label": "missing",
				"start": 3336,
				"end": 3343,
				"paired_with": {
					"file": "123456.html",
					"start": 3825,
					"end": 3831,
					"token": "defult",
					"label": "extra"
				},
				"timestamp": "13:37:00"
			}
		]
	},
	"student_files": {
		"123456.html": [
			{
				"token": "/",
				"label": "comment",
				"start": 589,
				"end": 590
			},
			{
				"token": "/",
				"label": "comment",
				"start": 590,
				"end": 591
			},
			{
				"token": "never",
				"label": "comment",
				"start": 592,
				"end": 597
			},
			{
				"token": "define",
				"label": "comment",
				"start": 598,
				"end": 604
			},
			{
				"token": "without",
				"label": "comment",
				"start": 605,
				"end": 612
			},
			{
				"token": "const",
				"label": "comment",
				"start": 613,
				"end": 618
			},
			{
				"token": ",",
				"label": "comment",
				"start": 618,
				"end": 619
			},
			{
				"token": "let",
				"label": "comment",
				"start": 620,
				"end": 623
			},
			{
				"token": "(",
				"label": "comment",
				"start": 624,
				"end": 625
			},
			{
				"token": "or",
				"label": "comment",
				"start": 625,
				"end": 627
			},
			{
				"token": "var",
				"label": "comment",
				"start": 628,
				"end": 631
			},
			{
				"token": ")",
				"label": "comment",
				"start": 631,
				"end": 632
			},
			{
				"token": "/",
				"label": "comment",
				"start": 816,
				"end": 817
			},
			{
				"token": "/",
				"label": "comment",
				"start": 817,
				"end": 818
			},
			{
				"token": "var",
				"label": "comment",
				"start": 819,
				"end": 822
			},
			{
				"token": "was",
				"label": "comment",
				"start": 823,
				"end": 826
			},
			{
				"token": "\"",
				"label": "comment",
				"start": 827,
				"end": 828
			},
			{
				"token": "replaced",
				"label": "comment",
				"start": 828,
				"end": 836
			},
			{
				"token": "\"",
				"label": "comment",
				"start": 836,
				"end": 837
			},
			{
				"token": "by",
				"label": "comment",
				"start": 838,
				"end": 840
			},
			{
				"token": "let",
				"label": "comment",
				"start": 841,
				"end": 844
			},
			{
				"token": "and",
				"label": "comment",
				"start": 845,
				"end": 848
			},
			{
				"token": "const",
				"label": "comment",
				"start": 849,
				"end": 854
			},
			{
				"token": "/",
				"label": "comment",
				"start": 904,
				"end": 905
			},
			{
				"token": "/",
				"label": "comment",
				"start": 905,
				"end": 906
			},
			{
				"token": "accepts",
				"label": "comment",
				"start": 907,
				"end": 914
			},
			{
				"token": "multiple",
				"label": "comment",
				"start": 915,
				"end": 923
			},
			{
				"token": "parameters",
				"label": "comment",
				"start": 924,
				"end": 934
			},
			{
				"token": "/",
				"label": "comment",
				"start": 1133,
				"end": 1134
			},
			{
				"token": "/",
				"label": "comment",
				"start": 1134,
				"end": 1135
			},
			{
				"token": "zero",
				"label": "comment",
				"start": 1136,
				"end": 1140
			},
			{
				"token": "is",
				"label": "comment",
				"start": 1141,
				"end": 1143
			},
			{
				"token": "\"",
				"label": "comment",
				"start": 1144,
				"end": 1145
			},
			{
				"token": "falsy",
				"label": "comment",
				"start": 1145,
				"end": 1150
			},
			{
				"token": "\"",
				"label": "comment",
				"start": 1150,
				"end": 1151
			},
			{
				"token": "/",
				"label": "comment",
				"start": 1161,
				"end": 1162
			},
			{
				"token": "/",
				"label": "comment",
				"start": 1162,
				"end": 1163
			},
			{
				"token": "arrays",
				"label": "comment",
				"start": 1164,
				"end": 1170
			},
			{
				"token": "are",
				"label": "comment",
				"start": 1171,
				"end": 1174
			},
			{
				"token": "like",
				"label": "comment",
				"start": 1175,
				"end": 1179
			},
			{
				"token": "Python",
				"label": "comment",
				"start": 1180,
				"end": 1186
			},
			{
				"token": "lists",
				"label": "comment",
				"start": 1187,
				"end": 1192
			},
			{
				"token": "/",
				"label": "comment",
				"start": 1360,
				"end": 1361
			},
			{
				"token": "/",
				"label": "comment",
				"start": 1361,
				"end": 1362
			},
			{
				"token": "myArray",
				"label": "comment",
				"start": 1363,
				"end": 1370
			},
			{
				"token": "=",
				"label": "comment",
				"start": 1371,
				"end": 1372
			},
			{
				"token": "[",
				"label": "comment",
				"start": 1373,
				"end": 1374
			},
			{
				"token": "1",
				"label": "comment",
				"start": 1374,
				"end": 1375
			},
			{
				"token": ",",
				"label": "comment",
				"start": 1375,
				"end": 1376
			},
			{
				"token": "2",
				"label": "comment",
				"start": 1377,
				"end": 1378
			},
			{
				"token": ",",
				"label": "comment",
				"start": 1378,
				"end": 1379
			},
			{
				"token": "3",
				"label": "comment",
				"start": 1380,
				"end": 1381
			},
			{
				"token": "]",
				"label": "comment",
				"start": 1381,
				"end": 1382
			},
			{
				"token": ";",
				"label": "comment",
				"start": 1382,
				"end": 1383
			},
			{
				"token": "ERROR",
				"label": "comment",
				"start": 1384,
				"end": 1389
			},
			{
				"token": "!",
				"label": "comment",
				"start": 1389,
				"end": 1390
			},
			{
				"token": "Program",
				"label": "comment",
				"start": 1391,
				"end": 1398
			},
			{
				"token": "would",
				"label": "comment",
				"start": 1399,
				"end": 1404
			},
			{
				"token": "fail",
				"label": "comment",
				"start": 1405,
				"end": 1409
			},
			{
				"token": "here",
				"label": "comment",
				"start": 1410,
				"end": 1414
			},
			{
				"token": "!",
				"label": "comment",
				"start": 1414,
				"end": 1415
			},
			{
				"token": "log",
				"label": "ghost_extra",
				"start": 1507,
				"end": 1510,
				"paired_with": {
					"file": "reconstructed.html",
					"start": 1337,
					"end": 1340,
					"token": "log",
					"ghost": true
				},
				"removal_ts": "12:53:22"
			},
			{
				"token": "/",
				"label": "comment",
				"start": 1672,
				"end": 1673
			},
			{
				"token": "/",
				"label": "comment",
				"start": 1673,
				"end": 1674
			},
			{
				"token": "bojects",
				"label": "comment",
				"start": 1675,
				"end": 1682
			},
			{
				"token": "are",
				"label": "comment",
				"start": 1683,
				"end": 1686
			},
			{
				"token": "like",
				"label": "comment",
				"start": 1687,
				"end": 1691
			},
			{
				"token": "Python",
				"label": "comment",
				"start": 1692,
				"end": 1698
			},
			{
				"token": "dictionaries",
				"label": "comment",
				"start": 1699,
				"end": 1711
			},
			{
				"token": "/",
				"label": "comment",
				"start": 2208,
				"end": 2209
			},
			{
				"token": "*",
				"label": "comment",
				"start": 2209,
				"end": 2210
			},
			{
				"token": "no",
				"label": "comment",
				"start": 2219,
				"end": 2221
			},
			{
				"token": "need",
				"label": "comment",
				"start": 2222,
				"end": 2226
			},
			{
				"token": "for",
				"label": "comment",
				"start": 2227,
				"end": 2230
			},
			{
				"token": "document",
				"label": "comment",
				"start": 2231,
				"end": 2239
			},
			{
				"token": ".",
				"label": "comment",
				"start": 2239,
				"end": 2240
			},
			{
				"token": "getElementById",
				"label": "comment",
				"start": 2240,
				"end": 2254
			},
			{
				"token": "(",
				"label": "comment",
				"start": 2254,
				"end": 2255
			},
			{
				"token": "\"",
				"label": "comment",
				"start": 2255,
				"end": 2256
			},
			{
				"token": "container",
				"label": "comment",
				"start": 2256,
				"end": 2265
			},
			{
				"token": "\"",
				"label": "comment",
				"start": 2265,
				"end": 2266
			},
			{
				"token": ")",
				"label": "comment",
				"start": 2266,
				"end": 2267
			},
			{
				"token": "ids",
				"label": "comment",
				"start": 2276,
				"end": 2279
			},
			{
				"token": "that",
				"label": "comment",
				"start": 2280,
				"end": 2284
			},
			{
				"token": "are",
				"label": "comment",
				"start": 2285,
				"end": 2288
			},
			{
				"token": "valid",
				"label": "comment",
				"start": 2289,
				"end": 2294
			},
			{
				"token": "JS",
				"label": "comment",
				"start": 2295,
				"end": 2297
			},
			{
				"token": "names",
				"label": "comment",
				"start": 2298,
				"end": 2303
			},
			{
				"token": "are",
				"label": "comment",
				"start": 2304,
				"end": 2307
			},
			{
				"token": "automatically",
				"label": "comment",
				"start": 2308,
				"end": 2321
			},
			{
				"token": "global",
				"label": "comment",
				"start": 2322,
				"end": 2328
			},
			{
				"token": "variables",
				"label": "comment",
				"start": 2329,
				"end": 2338
			},
			{
				"token": "invalid",
				"label": "comment",
				"start": 2347,
				"end": 2354
			},
			{
				"token": "names",
				"label": "comment",
				"start": 2355,
				"end": 2360
			},
			{
				"token": ":",
				"label": "comment",
				"start": 2360,
				"end": 2361
			},
			{
				"token": "*",
				"label": "comment",
				"start": 2370,
				"end": 2371
			},
			{
				"token": "start",
				"label": "comment",
				"start": 2372,
				"end": 2377
			},
			{
				"token": "with",
				"label": "comment",
				"start": 2378,
				"end": 2382
			},
			{
				"token": "a",
				"label": "comment",
				"start": 2383,
				"end": 2384
			},
			{
				"token": "number",
				"label": "comment",
				"start": 2385,
				"end": 2391
			},
			{
				"token": "*",
				"label": "comment",
				"start": 2400,
				"end": 2401
			},
			{
				"token": "contain",
				"label": "comment",
				"start": 2402,
				"end": 2409
			},
			{
				"token": "spaces",
				"label": "comment",
				"start": 2410,
				"end": 2416
			},
			{
				"token": "or",
				"label": "comment",
				"start": 2417,
				"end": 2419
			},
			{
				"token": "special",
				"label": "comment",
				"start": 2420,
				"end": 2427
			},
			{
				"token": "characters",
				"label": "comment",
				"start": 2428,
				"end": 2438
			},
			{
				"token": "(",
				"label": "comment",
				"start": 2439,
				"end": 2440
			},
			{
				"token": "like",
				"label": "comment",
				"start": 2440,
				"end": 2444
			},
			{
				"token": "-",
				"label": "comment",
				"start": 2445,
				"end": 2446
			},
			{
				"token": ")",
				"label": "comment",
				"start": 2446,
				"end": 2447
			},
			{
				"token": "*",
				"label": "comment",
				"start": 2456,
				"end": 2457
			},
			{
				"token": "*",
				"label": "comment",
				"start": 2458,
				"end": 2459
			},
			{
				"token": "/",
				"label": "comment",
				"start": 2459,
				"end": 2460
			},
			{
				"token": "/",
				"label": "comment",
				"start": 2509,
				"end": 2510
			},
			{
				"token": "/",
				"label": "comment",
				"start": 2510,
				"end": 2511
			},
			{
				"token": ".",
				"label": "comment",
				"start": 2511,
				"end": 2512
			},
			{
				"token": "operators",
				"label": "comment",
				"start": 2513,
				"end": 2522
			},
			{
				"token": "/",
				"label": "comment",
				"start": 2596,
				"end": 2597
			},
			{
				"token": "/",
				"label": "comment",
				"start": 2597,
				"end": 2598
			},
			{
				"token": "concatenation",
				"label": "comment",
				"start": 2599,
				"end": 2612
			},
			{
				"token": "/",
				"label": "comment",
				"start": 3144,
				"end": 3145
			},
			{
				"token": "/",
				"label": "comment",
				"start": 3145,
				"end": 3146
			},
			{
				"token": "escaping",
				"label": "comment",
				"start": 3147,
				"end": 3155
			},
			{
				"token": "with",
				"label": "comment",
				"start": 3156,
				"end": 3160
			},
			{
				"token": "\\",
				"label": "comment",
				"start": 3160,
				"end": 3161
			},
			{
				"token": "/",
				"label": "comment",
				"start": 3316,
				"end": 3317
			},
			{
				"token": "/",
				"label": "comment",
				"start": 3317,
				"end": 3318
			},
			{
				"token": "template",
				"label": "comment",
				"start": 3319,
				"end": 3327
			},
			{
				"token": "literal",
				"label": "comment",
				"start": 3328,
				"end": 3335
			},
			{
				"token": "defult",
				"label": "extra",
				"start": 3825,
				"end": 3831,
				"paired_with": {
					"file": "reconstructed.html",
					"start": 3336,
					"end": 3343,
					"token": "default",
					"label": "missing"
				}
			}
		]
	}
}
