{
  "token_matching": "lcs",
  "score": 81.1,
  "teacher_files": {
    "index.html": [
      {
        "token": "/",
        "label": "comment",
        "start": 73,
        "end": 74
      },
      {
        "token": "*",
        "label": "comment",
        "start": 74,
        "end": 75
      },
      {
        "token": "styling",
        "label": "comment",
        "start": 76,
        "end": 83
      },
      {
        "token": "by",
        "label": "comment",
        "start": 84,
        "end": 86
      },
      {
        "token": "ID",
        "label": "comment",
        "start": 87,
        "end": 89
      },
      {
        "token": "*",
        "label": "comment",
        "start": 90,
        "end": 91
      },
      {
        "token": "/",
        "label": "comment",
        "start": 91,
        "end": 92
      },
      {
        "token": "400px",
        "label": "missing",
        "start": 122,
        "end": 127,
        "insert_at": {
          "file": "123456.html",
          "pos": 167
        }
      },
      {
        "token": "/",
        "label": "comment",
        "start": 181,
        "end": 182
      },
      {
        "token": "*",
        "label": "comment",
        "start": 182,
        "end": 183
      },
      {
        "token": "CSS",
        "label": "comment",
        "start": 184,
        "end": 187
      },
      {
        "token": "class",
        "label": "comment",
        "start": 188,
        "end": 193
      },
      {
        "token": "*",
        "label": "comment",
        "start": 194,
        "end": 195
      },
      {
        "token": "/",
        "label": "comment",
        "start": 195,
        "end": 196
      },
      {
        "token": "50px",
        "label": "missing",
        "start": 220,
        "end": 224,
        "insert_at": {
          "file": "123456.html",
          "pos": 324
        }
      },
      {
        "token": "/",
        "label": "comment",
        "start": 247,
        "end": 248
      },
      {
        "token": "*",
        "label": "comment",
        "start": 248,
        "end": 249
      },
      {
        "token": "commented",
        "label": "comment",
        "start": 250,
        "end": 259
      },
      {
        "token": "styling",
        "label": "comment",
        "start": 260,
        "end": 267
      },
      {
        "token": "-",
        "label": "comment",
        "start": 268,
        "end": 269
      },
      {
        "token": "not",
        "label": "comment",
        "start": 270,
        "end": 273
      },
      {
        "token": "in",
        "label": "comment",
        "start": 274,
        "end": 276
      },
      {
        "token": "use",
        "label": "comment",
        "start": 277,
        "end": 280
      },
      {
        "token": "-",
        "label": "comment",
        "start": 281,
        "end": 282
      },
      {
        "token": "just",
        "label": "comment",
        "start": 283,
        "end": 287
      },
      {
        "token": "an",
        "label": "comment",
        "start": 288,
        "end": 290
      },
      {
        "token": "example",
        "label": "comment",
        "start": 291,
        "end": 298
      },
      {
        "token": "margin",
        "label": "comment",
        "start": 303,
        "end": 309
      },
      {
        "token": ":",
        "label": "comment",
        "start": 309,
        "end": 310
      },
      {
        "token": "10px",
        "label": "comment",
        "start": 311,
        "end": 315
      },
      {
        "token": ";",
        "label": "comment",
        "start": 315,
        "end": 316
      },
      {
        "token": "padding",
        "label": "comment",
        "start": 321,
        "end": 328
      },
      {
        "token": ":",
        "label": "comment",
        "start": 328,
        "end": 329
      },
      {
        "token": "5px",
        "label": "comment",
        "start": 330,
        "end": 333
      },
      {
        "token": ";",
        "label": "comment",
        "start": 333,
        "end": 334
      },
      {
        "token": "*",
        "label": "comment",
        "start": 335,
        "end": 336
      },
      {
        "token": "/",
        "label": "comment",
        "start": 336,
        "end": 337
      },
      {
        "token": "1px",
        "label": "missing",
        "start": 350,
        "end": 353,
        "insert_at": {
          "file": "123456.html",
          "pos": 515
        }
      },
      {
        "token": "/",
        "label": "comment",
        "start": 394,
        "end": 395
      },
      {
        "token": "*",
        "label": "comment",
        "start": 395,
        "end": 396
      },
      {
        "token": "size",
        "label": "comment",
        "start": 397,
        "end": 401
      },
      {
        "token": "includes",
        "label": "comment",
        "start": 402,
        "end": 410
      },
      {
        "token": "padding",
        "label": "comment",
        "start": 411,
        "end": 418
      },
      {
        "token": "and",
        "label": "comment",
        "start": 419,
        "end": 422
      },
      {
        "token": "border",
        "label": "comment",
        "start": 423,
        "end": 429
      },
      {
        "token": "*",
        "label": "comment",
        "start": 430,
        "end": 431
      },
      {
        "token": "/",
        "label": "comment",
        "start": 431,
        "end": 432
      },
      {
        "token": "white",
        "label": "missing",
        "start": 476,
        "end": 481,
        "insert_at": {
          "file": "123456.html",
          "pos": 715
        }
      },
      {
        "token": "black",
        "label": "missing",
        "start": 525,
        "end": 530,
        "insert_at": {
          "file": "123456.html",
          "pos": 799
        }
      },
      {
        "token": "dark",
        "label": "missing",
        "start": 1452,
        "end": 1456,
        "insert_at": {
          "file": "123456.html",
          "pos": 2171
        }
      },
      {
        "token": "\"",
        "label": "missing",
        "start": 1490,
        "end": 1491,
        "insert_at": {
          "file": "123456.html",
          "pos": 2232
        }
      },
      {
        "token": ">",
        "label": "missing",
        "start": 1491,
        "end": 1492,
        "insert_at": {
          "file": "123456.html",
          "pos": 2232
        }
      },
      {
        "token": "<",
        "label": "missing",
        "start": 1492,
        "end": 1493,
        "insert_at": {
          "file": "123456.html",
          "pos": 2232
        }
      },
      {
        "token": "/",
        "label": "missing",
        "start": 1493,
        "end": 1494,
        "insert_at": {
          "file": "123456.html",
          "pos": 2232
        }
      },
      {
        "token": "div",
        "label": "missing",
        "start": 1494,
        "end": 1497,
        "insert_at": {
          "file": "123456.html",
          "pos": 2232
        }
      },
      {
        "token": ">",
        "label": "missing",
        "start": 1497,
        "end": 1498,
        "insert_at": {
          "file": "123456.html",
          "pos": 2232
        }
      },
      {
        "token": "<",
        "label": "missing",
        "start": 1502,
        "end": 1503,
        "insert_at": {
          "file": "123456.html",
          "pos": 2232
        }
      },
      {
        "token": "div",
        "label": "missing",
        "start": 1503,
        "end": 1506,
        "insert_at": {
          "file": "123456.html",
          "pos": 2232
        }
      },
      {
        "token": "class",
        "label": "missing",
        "start": 1507,
        "end": 1512,
        "insert_at": {
          "file": "123456.html",
          "pos": 2232
        }
      },
      {
        "token": "=",
        "label": "missing",
        "start": 1512,
        "end": 1513,
        "insert_at": {
          "file": "123456.html",
          "pos": 2232
        }
      },
      {
        "token": "\"",
        "label": "missing",
        "start": 1513,
        "end": 1514,
        "insert_at": {
          "file": "123456.html",
          "pos": 2232
        }
      },
      {
        "token": "cell",
        "label": "missing",
        "start": 1514,
        "end": 1518,
        "insert_at": {
          "file": "123456.html",
          "pos": 2232
        }
      },
      {
        "token": "dark",
        "label": "missing",
        "start": 1519,
        "end": 1523,
        "insert_at": {
          "file": "123456.html",
          "pos": 2232
        }
      },
      {
        "token": "\"",
        "label": "missing",
        "start": 1523,
        "end": 1524,
        "insert_at": {
          "file": "123456.html",
          "pos": 2232
        }
      },
      {
        "token": ">",
        "label": "missing",
        "start": 1524,
        "end": 1525,
        "insert_at": {
          "file": "123456.html",
          "pos": 2232
        }
      },
      {
        "token": "<",
        "label": "missing",
        "start": 1525,
        "end": 1526,
        "insert_at": {
          "file": "123456.html",
          "pos": 2232
        }
      },
      {
        "token": "/",
        "label": "missing",
        "start": 1526,
        "end": 1527,
        "insert_at": {
          "file": "123456.html",
          "pos": 2232
        }
      },
      {
        "token": "div",
        "label": "missing",
        "start": 1527,
        "end": 1530,
        "insert_at": {
          "file": "123456.html",
          "pos": 2232
        }
      },
      {
        "token": ">",
        "label": "missing",
        "start": 1530,
        "end": 1531,
        "insert_at": {
          "file": "123456.html",
          "pos": 2232
        }
      },
      {
        "token": "<",
        "label": "missing",
        "start": 1535,
        "end": 1536,
        "insert_at": {
          "file": "123456.html",
          "pos": 2232
        }
      },
      {
        "token": "div",
        "label": "missing",
        "start": 1536,
        "end": 1539,
        "insert_at": {
          "file": "123456.html",
          "pos": 2232
        }
      },
      {
        "token": "class",
        "label": "missing",
        "start": 1540,
        "end": 1545,
        "insert_at": {
          "file": "123456.html",
          "pos": 2232
        }
      },
      {
        "token": "=",
        "label": "missing",
        "start": 1545,
        "end": 1546,
        "insert_at": {
          "file": "123456.html",
          "pos": 2232
        }
      },
      {
        "token": "\"",
        "label": "missing",
        "start": 1546,
        "end": 1547,
        "insert_at": {
          "file": "123456.html",
          "pos": 2232
        }
      },
      {
        "token": "cell",
        "label": "missing",
        "start": 1547,
        "end": 1551,
        "insert_at": {
          "file": "123456.html",
          "pos": 2232
        }
      },
      {
        "token": "light",
        "label": "missing",
        "start": 1552,
        "end": 1557,
        "insert_at": {
          "file": "123456.html",
          "pos": 2232
        }
      },
      {
        "token": "\"",
        "label": "missing",
        "start": 1557,
        "end": 1558,
        "insert_at": {
          "file": "123456.html",
          "pos": 2232
        }
      },
      {
        "token": ">",
        "label": "missing",
        "start": 1558,
        "end": 1559,
        "insert_at": {
          "file": "123456.html",
          "pos": 2232
        }
      },
      {
        "token": "<",
        "label": "missing",
        "start": 1559,
        "end": 1560,
        "insert_at": {
          "file": "123456.html",
          "pos": 2232
        }
      },
      {
        "token": "/",
        "label": "missing",
        "start": 1560,
        "end": 1561,
        "insert_at": {
          "file": "123456.html",
          "pos": 2232
        }
      },
      {
        "token": "div",
        "label": "missing",
        "start": 1561,
        "end": 1564,
        "insert_at": {
          "file": "123456.html",
          "pos": 2232
        }
      },
      {
        "token": ">",
        "label": "missing",
        "start": 1564,
        "end": 1565,
        "insert_at": {
          "file": "123456.html",
          "pos": 2232
        }
      },
      {
        "token": "<",
        "label": "missing",
        "start": 1569,
        "end": 1570,
        "insert_at": {
          "file": "123456.html",
          "pos": 2232
        }
      },
      {
        "token": "div",
        "label": "missing",
        "start": 1570,
        "end": 1573,
        "insert_at": {
          "file": "123456.html",
          "pos": 2232
        }
      },
      {
        "token": "class",
        "label": "missing",
        "start": 1574,
        "end": 1579,
        "insert_at": {
          "file": "123456.html",
          "pos": 2232
        }
      },
      {
        "token": "=",
        "label": "missing",
        "start": 1579,
        "end": 1580,
        "insert_at": {
          "file": "123456.html",
          "pos": 2232
        }
      },
      {
        "token": "\"",
        "label": "missing",
        "start": 1580,
        "end": 1581,
        "insert_at": {
          "file": "123456.html",
          "pos": 2232
        }
      },
      {
        "token": "cell",
        "label": "missing",
        "start": 1581,
        "end": 1585,
        "insert_at": {
          "file": "123456.html",
          "pos": 2232
        }
      },
      {
        "token": "dark",
        "label": "missing",
        "start": 1586,
        "end": 1590,
        "insert_at": {
          "file": "123456.html",
          "pos": 2232
        }
      },
      {
        "token": "\"",
        "label": "missing",
        "start": 1590,
        "end": 1591,
        "insert_at": {
          "file": "123456.html",
          "pos": 2232
        }
      },
      {
        "token": ">",
        "label": "missing",
        "start": 1591,
        "end": 1592,
        "insert_at": {
          "file": "123456.html",
          "pos": 2232
        }
      },
      {
        "token": "<",
        "label": "missing",
        "start": 1592,
        "end": 1593,
        "insert_at": {
          "file": "123456.html",
          "pos": 2232
        }
      },
      {
        "token": "/",
        "label": "missing",
        "start": 1593,
        "end": 1594,
        "insert_at": {
          "file": "123456.html",
          "pos": 2232
        }
      },
      {
        "token": "div",
        "label": "missing",
        "start": 1594,
        "end": 1597,
        "insert_at": {
          "file": "123456.html",
          "pos": 2232
        }
      },
      {
        "token": ">",
        "label": "missing",
        "start": 1597,
        "end": 1598,
        "insert_at": {
          "file": "123456.html",
          "pos": 2232
        }
      },
      {
        "token": "<",
        "label": "missing",
        "start": 1602,
        "end": 1603,
        "insert_at": {
          "file": "123456.html",
          "pos": 2232
        }
      },
      {
        "token": "div",
        "label": "missing",
        "start": 1603,
        "end": 1606,
        "insert_at": {
          "file": "123456.html",
          "pos": 2232
        }
      },
      {
        "token": "class",
        "label": "missing",
        "start": 1607,
        "end": 1612,
        "insert_at": {
          "file": "123456.html",
          "pos": 2232
        }
      },
      {
        "token": "=",
        "label": "missing",
        "start": 1612,
        "end": 1613,
        "insert_at": {
          "file": "123456.html",
          "pos": 2232
        }
      },
      {
        "token": "\"",
        "label": "missing",
        "start": 1613,
        "end": 1614,
        "insert_at": {
          "file": "123456.html",
          "pos": 2232
        }
      },
      {
        "token": "cell",
        "label": "missing",
        "start": 1614,
        "end": 1618,
        "insert_at": {
          "file": "123456.html",
          "pos": 2232
        }
      },
      {
        "token": "light",
        "label": "missing",
        "start": 1619,
        "end": 1624,
        "insert_at": {
          "file": "123456.html",
          "pos": 2232
        }
      },
      {
        "token": "\"",
        "label": "missing",
        "start": 1624,
        "end": 1625,
        "insert_at": {
          "file": "123456.html",
          "pos": 2232
        }
      },
      {
        "token": ">",
        "label": "missing",
        "start": 1625,
        "end": 1626,
        "insert_at": {
          "file": "123456.html",
          "pos": 2232
        }
      },
      {
        "token": "<",
        "label": "missing",
        "start": 1626,
        "end": 1627,
        "insert_at": {
          "file": "123456.html",
          "pos": 2232
        }
      },
      {
        "token": "/",
        "label": "missing",
        "start": 1627,
        "end": 1628,
        "insert_at": {
          "file": "123456.html",
          "pos": 2232
        }
      },
      {
        "token": "div",
        "label": "missing",
        "start": 1628,
        "end": 1631,
        "insert_at": {
          "file": "123456.html",
          "pos": 2232
        }
      },
      {
        "token": ">",
        "label": "missing",
        "start": 1631,
        "end": 1632,
        "insert_at": {
          "file": "123456.html",
          "pos": 2232
        }
      },
      {
        "token": "<",
        "label": "missing",
        "start": 1636,
        "end": 1637,
        "insert_at": {
          "file": "123456.html",
          "pos": 2232
        }
      },
      {
        "token": "div",
        "label": "missing",
        "start": 1637,
        "end": 1640,
        "insert_at": {
          "file": "123456.html",
          "pos": 2232
        }
      },
      {
        "token": "class",
        "label": "missing",
        "start": 1641,
        "end": 1646,
        "insert_at": {
          "file": "123456.html",
          "pos": 2232
        }
      },
      {
        "token": "=",
        "label": "missing",
        "start": 1646,
        "end": 1647,
        "insert_at": {
          "file": "123456.html",
          "pos": 2232
        }
      },
      {
        "token": "\"",
        "label": "missing",
        "start": 1647,
        "end": 1648,
        "insert_at": {
          "file": "123456.html",
          "pos": 2232
        }
      },
      {
        "token": "cell",
        "label": "missing",
        "start": 1648,
        "end": 1652,
        "insert_at": {
          "file": "123456.html",
          "pos": 2232
        }
      },
      {
        "token": "dark",
        "label": "missing",
        "start": 1653,
        "end": 1657,
        "insert_at": {
          "file": "123456.html",
          "pos": 2232
        }
      },
      {
        "token": "\"",
        "label": "missing",
        "start": 1657,
        "end": 1658,
        "insert_at": {
          "file": "123456.html",
          "pos": 2232
        }
      },
      {
        "token": ">",
        "label": "missing",
        "start": 1658,
        "end": 1659,
        "insert_at": {
          "file": "123456.html",
          "pos": 2232
        }
      },
      {
        "token": "<",
        "label": "missing",
        "start": 1659,
        "end": 1660,
        "insert_at": {
          "file": "123456.html",
          "pos": 2232
        }
      },
      {
        "token": "/",
        "label": "missing",
        "start": 1660,
        "end": 1661,
        "insert_at": {
          "file": "123456.html",
          "pos": 2232
        }
      },
      {
        "token": "div",
        "label": "missing",
        "start": 1661,
        "end": 1664,
        "insert_at": {
          "file": "123456.html",
          "pos": 2232
        }
      },
      {
        "token": ">",
        "label": "missing",
        "start": 1664,
        "end": 1665,
        "insert_at": {
          "file": "123456.html",
          "pos": 2232
        }
      },
      {
        "token": "<",
        "label": "missing",
        "start": 1669,
        "end": 1670,
        "insert_at": {
          "file": "123456.html",
          "pos": 2232
        }
      },
      {
        "token": "div",
        "label": "missing",
        "start": 1670,
        "end": 1673,
        "insert_at": {
          "file": "123456.html",
          "pos": 2232
        }
      },
      {
        "token": "class",
        "label": "missing",
        "start": 1674,
        "end": 1679,
        "insert_at": {
          "file": "123456.html",
          "pos": 2232
        }
      },
      {
        "token": "=",
        "label": "missing",
        "start": 1679,
        "end": 1680,
        "insert_at": {
          "file": "123456.html",
          "pos": 2232
        }
      },
      {
        "token": "\"",
        "label": "missing",
        "start": 1680,
        "end": 1681,
        "insert_at": {
          "file": "123456.html",
          "pos": 2232
        }
      },
      {
        "token": "cell",
        "label": "missing",
        "start": 1681,
        "end": 1685,
        "insert_at": {
          "file": "123456.html",
          "pos": 2232
        }
      },
      {
        "token": "light",
        "label": "missing",
        "start": 1686,
        "end": 1691,
        "insert_at": {
          "file": "123456.html",
          "pos": 2232
        }
      },
      {
        "token": "\"",
        "label": "missing",
        "start": 1691,
        "end": 1692,
        "insert_at": {
          "file": "123456.html",
          "pos": 2232
        }
      },
      {
        "token": ">",
        "label": "missing",
        "start": 1692,
        "end": 1693,
        "insert_at": {
          "file": "123456.html",
          "pos": 2232
        }
      },
      {
        "token": "<",
        "label": "missing",
        "start": 1693,
        "end": 1694,
        "insert_at": {
          "file": "123456.html",
          "pos": 2232
        }
      },
      {
        "token": "/",
        "label": "missing",
        "start": 1694,
        "end": 1695,
        "insert_at": {
          "file": "123456.html",
          "pos": 2232
        }
      },
      {
        "token": "div",
        "label": "missing",
        "start": 1695,
        "end": 1698,
        "insert_at": {
          "file": "123456.html",
          "pos": 2232
        }
      },
      {
        "token": ">",
        "label": "missing",
        "start": 1698,
        "end": 1699,
        "insert_at": {
          "file": "123456.html",
          "pos": 2232
        }
      },
      {
        "token": "<",
        "label": "missing",
        "start": 1707,
        "end": 1708,
        "insert_at": {
          "file": "123456.html",
          "pos": 2232
        }
      },
      {
        "token": "div",
        "label": "missing",
        "start": 1708,
        "end": 1711,
        "insert_at": {
          "file": "123456.html",
          "pos": 2232
        }
      },
      {
        "token": "class",
        "label": "missing",
        "start": 1712,
        "end": 1717,
        "insert_at": {
          "file": "123456.html",
          "pos": 2232
        }
      },
      {
        "token": "=",
        "label": "missing",
        "start": 1717,
        "end": 1718,
        "insert_at": {
          "file": "123456.html",
          "pos": 2232
        }
      },
      {
        "token": "\"",
        "label": "missing",
        "start": 1718,
        "end": 1719,
        "insert_at": {
          "file": "123456.html",
          "pos": 2232
        }
      },
      {
        "token": "cell",
        "label": "missing",
        "start": 1719,
        "end": 1723,
        "insert_at": {
          "file": "123456.html",
          "pos": 2232
        }
      },
      {
        "token": "light",
        "label": "missing",
        "start": 1724,
        "end": 1729,
        "insert_at": {
          "file": "123456.html",
          "pos": 2232
        }
      },
      {
        "token": "\"",
        "label": "missing",
        "start": 1729,
        "end": 1730,
        "insert_at": {
          "file": "123456.html",
          "pos": 2232
        }
      },
      {
        "token": ">",
        "label": "missing",
        "start": 1730,
        "end": 1731,
        "insert_at": {
          "file": "123456.html",
          "pos": 2232
        }
      },
      {
        "token": "<",
        "label": "missing",
        "start": 1731,
        "end": 1732,
        "insert_at": {
          "file": "123456.html",
          "pos": 2232
        }
      },
      {
        "token": "/",
        "label": "missing",
        "start": 1732,
        "end": 1733,
        "insert_at": {
          "file": "123456.html",
          "pos": 2232
        }
      },
      {
        "token": "div",
        "label": "missing",
        "start": 1733,
        "end": 1736,
        "insert_at": {
          "file": "123456.html",
          "pos": 2232
        }
      },
      {
        "token": ">",
        "label": "missing",
        "start": 1736,
        "end": 1737,
        "insert_at": {
          "file": "123456.html",
          "pos": 2232
        }
      },
      {
        "token": "<",
        "label": "missing",
        "start": 1741,
        "end": 1742,
        "insert_at": {
          "file": "123456.html",
          "pos": 2232
        }
      },
      {
        "token": "div",
        "label": "missing",
        "start": 1742,
        "end": 1745,
        "insert_at": {
          "file": "123456.html",
          "pos": 2232
        }
      },
      {
        "token": "class",
        "label": "missing",
        "start": 1746,
        "end": 1751,
        "insert_at": {
          "file": "123456.html",
          "pos": 2232
        }
      },
      {
        "token": "=",
        "label": "missing",
        "start": 1751,
        "end": 1752,
        "insert_at": {
          "file": "123456.html",
          "pos": 2232
        }
      },
      {
        "token": "\"",
        "label": "missing",
        "start": 1752,
        "end": 1753,
        "insert_at": {
          "file": "123456.html",
          "pos": 2232
        }
      },
      {
        "token": "cell",
        "label": "missing",
        "start": 1753,
        "end": 1757,
        "insert_at": {
          "file": "123456.html",
          "pos": 2232
        }
      },
      {
        "token": "dark",
        "label": "missing",
        "start": 1758,
        "end": 1762,
        "insert_at": {
          "file": "123456.html",
          "pos": 2232
        }
      },
      {
        "token": "\"",
        "label": "missing",
        "start": 1762,
        "end": 1763,
        "insert_at": {
          "file": "123456.html",
          "pos": 2232
        }
      },
      {
        "token": ">",
        "label": "missing",
        "start": 1763,
        "end": 1764,
        "insert_at": {
          "file": "123456.html",
          "pos": 2232
        }
      },
      {
        "token": "<",
        "label": "missing",
        "start": 1764,
        "end": 1765,
        "insert_at": {
          "file": "123456.html",
          "pos": 2232
        }
      },
      {
        "token": "/",
        "label": "missing",
        "start": 1765,
        "end": 1766,
        "insert_at": {
          "file": "123456.html",
          "pos": 2232
        }
      },
      {
        "token": "div",
        "label": "missing",
        "start": 1766,
        "end": 1769,
        "insert_at": {
          "file": "123456.html",
          "pos": 2232
        }
      },
      {
        "token": ">",
        "label": "missing",
        "start": 1769,
        "end": 1770,
        "insert_at": {
          "file": "123456.html",
          "pos": 2232
        }
      },
      {
        "token": "<",
        "label": "missing",
        "start": 1774,
        "end": 1775,
        "insert_at": {
          "file": "123456.html",
          "pos": 2232
        }
      },
      {
        "token": "div",
        "label": "missing",
        "start": 1775,
        "end": 1778,
        "insert_at": {
          "file": "123456.html",
          "pos": 2232
        }
      },
      {
        "token": "class",
        "label": "missing",
        "start": 1779,
        "end": 1784,
        "insert_at": {
          "file": "123456.html",
          "pos": 2232
        }
      },
      {
        "token": "=",
        "label": "missing",
        "start": 1784,
        "end": 1785,
        "insert_at": {
          "file": "123456.html",
          "pos": 2232
        }
      },
      {
        "token": "\"",
        "label": "missing",
        "start": 1785,
        "end": 1786,
        "insert_at": {
          "file": "123456.html",
          "pos": 2232
        }
      },
      {
        "token": "cell",
        "label": "missing",
        "start": 1786,
        "end": 1790,
        "insert_at": {
          "file": "123456.html",
          "pos": 2232
        }
      },
      {
        "token": "light",
        "label": "missing",
        "start": 1791,
        "end": 1796,
        "insert_at": {
          "file": "123456.html",
          "pos": 2232
        }
      },
      {
        "token": "\"",
        "label": "missing",
        "start": 1796,
        "end": 1797,
        "insert_at": {
          "file": "123456.html",
          "pos": 2232
        }
      },
      {
        "token": ">",
        "label": "missing",
        "start": 1797,
        "end": 1798,
        "insert_at": {
          "file": "123456.html",
          "pos": 2232
        }
      },
      {
        "token": "<",
        "label": "missing",
        "start": 1798,
        "end": 1799,
        "insert_at": {
          "file": "123456.html",
          "pos": 2232
        }
      },
      {
        "token": "/",
        "label": "missing",
        "start": 1799,
        "end": 1800,
        "insert_at": {
          "file": "123456.html",
          "pos": 2232
        }
      },
      {
        "token": "div",
        "label": "missing",
        "start": 1800,
        "end": 1803,
        "insert_at": {
          "file": "123456.html",
          "pos": 2232
        }
      },
      {
        "token": ">",
        "label": "missing",
        "start": 1803,
        "end": 1804,
        "insert_at": {
          "file": "123456.html",
          "pos": 2232
        }
      },
      {
        "token": "<",
        "label": "missing",
        "start": 1808,
        "end": 1809,
        "insert_at": {
          "file": "123456.html",
          "pos": 2232
        }
      },
      {
        "token": "div",
        "label": "missing",
        "start": 1809,
        "end": 1812,
        "insert_at": {
          "file": "123456.html",
          "pos": 2232
        }
      },
      {
        "token": "class",
        "label": "missing",
        "start": 1813,
        "end": 1818,
        "insert_at": {
          "file": "123456.html",
          "pos": 2232
        }
      },
      {
        "token": "=",
        "label": "missing",
        "start": 1818,
        "end": 1819,
        "insert_at": {
          "file": "123456.html",
          "pos": 2232
        }
      },
      {
        "token": "\"",
        "label": "missing",
        "start": 1819,
        "end": 1820,
        "insert_at": {
          "file": "123456.html",
          "pos": 2232
        }
      },
      {
        "token": "cell",
        "label": "missing",
        "start": 1820,
        "end": 1824,
        "insert_at": {
          "file": "123456.html",
          "pos": 2232
        }
      },
      {
        "token": "dark",
        "label": "missing",
        "start": 1825,
        "end": 1829,
        "insert_at": {
          "file": "123456.html",
          "pos": 2232
        }
      },
      {
        "token": "\"",
        "label": "missing",
        "start": 1829,
        "end": 1830,
        "insert_at": {
          "file": "123456.html",
          "pos": 2232
        }
      },
      {
        "token": ">",
        "label": "missing",
        "start": 1830,
        "end": 1831,
        "insert_at": {
          "file": "123456.html",
          "pos": 2232
        }
      },
      {
        "token": "<",
        "label": "missing",
        "start": 1831,
        "end": 1832,
        "insert_at": {
          "file": "123456.html",
          "pos": 2232
        }
      },
      {
        "token": "/",
        "label": "missing",
        "start": 1832,
        "end": 1833,
        "insert_at": {
          "file": "123456.html",
          "pos": 2232
        }
      },
      {
        "token": "div",
        "label": "missing",
        "start": 1833,
        "end": 1836,
        "insert_at": {
          "file": "123456.html",
          "pos": 2232
        }
      },
      {
        "token": ">",
        "label": "missing",
        "start": 1836,
        "end": 1837,
        "insert_at": {
          "file": "123456.html",
          "pos": 2232
        }
      },
      {
        "token": "<",
        "label": "missing",
        "start": 1841,
        "end": 1842,
        "insert_at": {
          "file": "123456.html",
          "pos": 2232
        }
      },
      {
        "token": "div",
        "label": "missing",
        "start": 1842,
        "end": 1845,
        "insert_at": {
          "file": "123456.html",
          "pos": 2232
        }
      },
      {
        "token": "class",
        "label": "missing",
        "start": 1846,
        "end": 1851,
        "insert_at": {
          "file": "123456.html",
          "pos": 2232
        }
      },
      {
        "token": "=",
        "label": "missing",
        "start": 1851,
        "end": 1852,
        "insert_at": {
          "file": "123456.html",
          "pos": 2232
        }
      },
      {
        "token": "\"",
        "label": "missing",
        "start": 1852,
        "end": 1853,
        "insert_at": {
          "file": "123456.html",
          "pos": 2232
        }
      },
      {
        "token": "cell",
        "label": "missing",
        "start": 1853,
        "end": 1857,
        "insert_at": {
          "file": "123456.html",
          "pos": 2232
        }
      },
      {
        "token": "light",
        "label": "missing",
        "start": 1858,
        "end": 1863,
        "insert_at": {
          "file": "123456.html",
          "pos": 2232
        }
      },
      {
        "token": "\"",
        "label": "missing",
        "start": 1863,
        "end": 1864,
        "insert_at": {
          "file": "123456.html",
          "pos": 2232
        }
      },
      {
        "token": ">",
        "label": "missing",
        "start": 1864,
        "end": 1865,
        "insert_at": {
          "file": "123456.html",
          "pos": 2232
        }
      },
      {
        "token": "<",
        "label": "missing",
        "start": 1865,
        "end": 1866,
        "insert_at": {
          "file": "123456.html",
          "pos": 2232
        }
      },
      {
        "token": "/",
        "label": "missing",
        "start": 1866,
        "end": 1867,
        "insert_at": {
          "file": "123456.html",
          "pos": 2232
        }
      },
      {
        "token": "div",
        "label": "missing",
        "start": 1867,
        "end": 1870,
        "insert_at": {
          "file": "123456.html",
          "pos": 2232
        }
      },
      {
        "token": ">",
        "label": "missing",
        "start": 1870,
        "end": 1871,
        "insert_at": {
          "file": "123456.html",
          "pos": 2232
        }
      },
      {
        "token": "<",
        "label": "missing",
        "start": 1875,
        "end": 1876,
        "insert_at": {
          "file": "123456.html",
          "pos": 2232
        }
      },
      {
        "token": "div",
        "label": "missing",
        "start": 1876,
        "end": 1879,
        "insert_at": {
          "file": "123456.html",
          "pos": 2232
        }
      },
      {
        "token": "class",
        "label": "missing",
        "start": 1880,
        "end": 1885,
        "insert_at": {
          "file": "123456.html",
          "pos": 2232
        }
      },
      {
        "token": "=",
        "label": "missing",
        "start": 1885,
        "end": 1886,
        "insert_at": {
          "file": "123456.html",
          "pos": 2232
        }
      },
      {
        "token": "\"",
        "label": "missing",
        "start": 1886,
        "end": 1887,
        "insert_at": {
          "file": "123456.html",
          "pos": 2232
        }
      },
      {
        "token": "cell",
        "label": "missing",
        "start": 1887,
        "end": 1891,
        "insert_at": {
          "file": "123456.html",
          "pos": 2232
        }
      },
      {
        "token": "dark",
        "label": "missing",
        "start": 1892,
        "end": 1896,
        "insert_at": {
          "file": "123456.html",
          "pos": 2232
        }
      },
      {
        "token": "\"",
        "label": "missing",
        "start": 1896,
        "end": 1897,
        "insert_at": {
          "file": "123456.html",
          "pos": 2232
        }
      },
      {
        "token": ">",
        "label": "missing",
        "start": 1897,
        "end": 1898,
        "insert_at": {
          "file": "123456.html",
          "pos": 2232
        }
      },
      {
        "token": "<",
        "label": "missing",
        "start": 1898,
        "end": 1899,
        "insert_at": {
          "file": "123456.html",
          "pos": 2232
        }
      },
      {
        "token": "/",
        "label": "missing",
        "start": 1899,
        "end": 1900,
        "insert_at": {
          "file": "123456.html",
          "pos": 2232
        }
      },
      {
        "token": "div",
        "label": "missing",
        "start": 1900,
        "end": 1903,
        "insert_at": {
          "file": "123456.html",
          "pos": 2232
        }
      },
      {
        "token": ">",
        "label": "missing",
        "start": 1903,
        "end": 1904,
        "insert_at": {
          "file": "123456.html",
          "pos": 2232
        }
      },
      {
        "token": "<",
        "label": "missing",
        "start": 1908,
        "end": 1909,
        "insert_at": {
          "file": "123456.html",
          "pos": 2232
        }
      },
      {
        "token": "div",
        "label": "missing",
        "start": 1909,
        "end": 1912,
        "insert_at": {
          "file": "123456.html",
          "pos": 2232
        }
      },
      {
        "token": "class",
        "label": "missing",
        "start": 1913,
        "end": 1918,
        "insert_at": {
          "file": "123456.html",
          "pos": 2232
        }
      },
      {
        "token": "=",
        "label": "missing",
        "start": 1918,
        "end": 1919,
        "insert_at": {
          "file": "123456.html",
          "pos": 2232
        }
      },
      {
        "token": "\"",
        "label": "missing",
        "start": 1919,
        "end": 1920,
        "insert_at": {
          "file": "123456.html",
          "pos": 2232
        }
      },
      {
        "token": "cell",
        "label": "missing",
        "start": 1920,
        "end": 1924,
        "insert_at": {
          "file": "123456.html",
          "pos": 2232
        }
      },
      {
        "token": "light",
        "label": "missing",
        "start": 1925,
        "end": 1930,
        "insert_at": {
          "file": "123456.html",
          "pos": 2232
        }
      },
      {
        "token": "\"",
        "label": "missing",
        "start": 1930,
        "end": 1931,
        "insert_at": {
          "file": "123456.html",
          "pos": 2232
        }
      },
      {
        "token": ">",
        "label": "missing",
        "start": 1931,
        "end": 1932,
        "insert_at": {
          "file": "123456.html",
          "pos": 2232
        }
      },
      {
        "token": "<",
        "label": "missing",
        "start": 1932,
        "end": 1933,
        "insert_at": {
          "file": "123456.html",
          "pos": 2232
        }
      },
      {
        "token": "/",
        "label": "missing",
        "start": 1933,
        "end": 1934,
        "insert_at": {
          "file": "123456.html",
          "pos": 2232
        }
      },
      {
        "token": "div",
        "label": "missing",
        "start": 1934,
        "end": 1937,
        "insert_at": {
          "file": "123456.html",
          "pos": 2232
        }
      },
      {
        "token": ">",
        "label": "missing",
        "start": 1937,
        "end": 1938,
        "insert_at": {
          "file": "123456.html",
          "pos": 2232
        }
      },
      {
        "token": "<",
        "label": "missing",
        "start": 1942,
        "end": 1943,
        "insert_at": {
          "file": "123456.html",
          "pos": 2232
        }
      },
      {
        "token": "div",
        "label": "missing",
        "start": 1943,
        "end": 1946,
        "insert_at": {
          "file": "123456.html",
          "pos": 2232
        }
      },
      {
        "token": "class",
        "label": "missing",
        "start": 1947,
        "end": 1952,
        "insert_at": {
          "file": "123456.html",
          "pos": 2232
        }
      },
      {
        "token": "=",
        "label": "missing",
        "start": 1952,
        "end": 1953,
        "insert_at": {
          "file": "123456.html",
          "pos": 2232
        }
      },
      {
        "token": "\"",
        "label": "missing",
        "start": 1953,
        "end": 1954,
        "insert_at": {
          "file": "123456.html",
          "pos": 2232
        }
      },
      {
        "token": "cell",
        "label": "missing",
        "start": 1954,
        "end": 1958,
        "insert_at": {
          "file": "123456.html",
          "pos": 2232
        }
      },
      {
        "token": "dark",
        "label": "missing",
        "start": 1959,
        "end": 1963,
        "insert_at": {
          "file": "123456.html",
          "pos": 2232
        }
      },
      {
        "token": "<",
        "label": "comment",
        "start": 2802,
        "end": 2803
      },
      {
        "token": "!",
        "label": "comment",
        "start": 2803,
        "end": 2804
      },
      {
        "token": "-",
        "label": "comment",
        "start": 2804,
        "end": 2805
      },
      {
        "token": "-",
        "label": "comment",
        "start": 2805,
        "end": 2806
      },
      {
        "token": "div",
        "label": "comment",
        "start": 2807,
        "end": 2810
      },
      {
        "token": "with",
        "label": "comment",
        "start": 2811,
        "end": 2815
      },
      {
        "token": "Inline",
        "label": "comment",
        "start": 2816,
        "end": 2822
      },
      {
        "token": "Style",
        "label": "comment",
        "start": 2823,
        "end": 2828
      },
      {
        "token": "(",
        "label": "comment",
        "start": 2829,
        "end": 2830
      },
      {
        "token": "not",
        "label": "comment",
        "start": 2830,
        "end": 2833
      },
      {
        "token": "recommended",
        "label": "comment",
        "start": 2834,
        "end": 2845
      },
      {
        "token": ")",
        "label": "comment",
        "start": 2845,
        "end": 2846
      },
      {
        "token": "<",
        "label": "comment",
        "start": 2849,
        "end": 2850
      },
      {
        "token": "div",
        "label": "comment",
        "start": 2850,
        "end": 2853
      },
      {
        "token": "style",
        "label": "comment",
        "start": 2854,
        "end": 2859
      },
      {
        "token": "=",
        "label": "comment",
        "start": 2859,
        "end": 2860
      },
      {
        "token": "\"",
        "label": "comment",
        "start": 2860,
        "end": 2861
      },
      {
        "token": "height",
        "label": "comment",
        "start": 2861,
        "end": 2867
      },
      {
        "token": ":",
        "label": "comment",
        "start": 2867,
        "end": 2868
      },
      {
        "token": "50px",
        "label": "comment",
        "start": 2869,
        "end": 2873
      },
      {
        "token": ";",
        "label": "comment",
        "start": 2873,
        "end": 2874
      },
      {
        "token": "background",
        "label": "comment",
        "start": 2878,
        "end": 2888
      },
      {
        "token": "-",
        "label": "comment",
        "start": 2888,
        "end": 2889
      },
      {
        "token": "color",
        "label": "comment",
        "start": 2889,
        "end": 2894
      },
      {
        "token": ":",
        "label": "comment",
        "start": 2894,
        "end": 2895
      },
      {
        "token": "black",
        "label": "comment",
        "start": 2896,
        "end": 2901
      },
      {
        "token": ";",
        "label": "comment",
        "start": 2901,
        "end": 2902
      },
      {
        "token": "width",
        "label": "comment",
        "start": 2906,
        "end": 2911
      },
      {
        "token": ":",
        "label": "comment",
        "start": 2911,
        "end": 2912
      },
      {
        "token": "50px",
        "label": "comment",
        "start": 2913,
        "end": 2917
      },
      {
        "token": ";",
        "label": "comment",
        "start": 2917,
        "end": 2918
      },
      {
        "token": "\"",
        "label": "comment",
        "start": 2918,
        "end": 2919
      },
      {
        "token": ">",
        "label": "comment",
        "start": 2922,
        "end": 2923
      },
      {
        "token": "<",
        "label": "comment",
        "start": 2923,
        "end": 2924
      },
      {
        "token": "/",
        "label": "comment",
        "start": 2924,
        "end": 2925
      },
      {
        "token": "div",
        "label": "comment",
        "start": 2925,
        "end": 2928
      },
      {
        "token": ">",
        "label": "comment",
        "start": 2928,
        "end": 2929
      },
      {
        "token": "-",
        "label": "comment",
        "start": 2930,
        "end": 2931
      },
      {
        "token": "-",
        "label": "comment",
        "start": 2931,
        "end": 2932
      },
      {
        "token": ">",
        "label": "comment",
        "start": 2932,
        "end": 2933
      }
    ]
  },
  "student_files": {
    "123456.html": [
      {
        "token": "/",
        "label": "comment",
        "start": 97,
        "end": 98
      },
      {
        "token": "*",
        "label": "comment",
        "start": 98,
        "end": 99
      },
      {
        "token": "styling",
        "label": "comment",
        "start": 100,
        "end": 107
      },
      {
        "token": "by",
        "label": "comment",
        "start": 108,
        "end": 110
      },
      {
        "token": "ID",
        "label": "comment",
        "start": 111,
        "end": 113
      },
      {
        "token": "*",
        "label": "comment",
        "start": 114,
        "end": 115
      },
      {
        "token": "/",
        "label": "comment",
        "start": 115,
        "end": 116
      },
      {
        "token": "425px",
        "label": "extra",
        "start": 167,
        "end": 172
      },
      {
        "token": "/",
        "label": "comment",
        "start": 264,
        "end": 265
      },
      {
        "token": "*",
        "label": "comment",
        "start": 265,
        "end": 266
      },
      {
        "token": "CSS",
        "label": "comment",
        "start": 267,
        "end": 270
      },
      {
        "token": "class",
        "label": "comment",
        "start": 271,
        "end": 276
      },
      {
        "token": "*",
        "label": "comment",
        "start": 277,
        "end": 278
      },
      {
        "token": "/",
        "label": "comment",
        "start": 278,
        "end": 279
      },
      {
        "token": "25px",
        "label": "extra",
        "start": 324,
        "end": 328
      },
      {
        "token": "/",
        "label": "comment",
        "start": 375,
        "end": 376
      },
      {
        "token": "*",
        "label": "comment",
        "start": 376,
        "end": 377
      },
      {
        "token": "commented",
        "label": "comment",
        "start": 378,
        "end": 387
      },
      {
        "token": "styling",
        "label": "comment",
        "start": 388,
        "end": 395
      },
      {
        "token": "-",
        "label": "comment",
        "start": 396,
        "end": 397
      },
      {
        "token": "not",
        "label": "comment",
        "start": 398,
        "end": 401
      },
      {
        "token": "in",
        "label": "comment",
        "start": 402,
        "end": 404
      },
      {
        "token": "use",
        "label": "comment",
        "start": 405,
        "end": 408
      },
      {
        "token": "-",
        "label": "comment",
        "start": 409,
        "end": 410
      },
      {
        "token": "just",
        "label": "comment",
        "start": 411,
        "end": 415
      },
      {
        "token": "an",
        "label": "comment",
        "start": 416,
        "end": 418
      },
      {
        "token": "example",
        "label": "comment",
        "start": 419,
        "end": 426
      },
      {
        "token": "margin",
        "label": "comment",
        "start": 444,
        "end": 450
      },
      {
        "token": ":",
        "label": "comment",
        "start": 450,
        "end": 451
      },
      {
        "token": "10px",
        "label": "comment",
        "start": 452,
        "end": 456
      },
      {
        "token": ";",
        "label": "comment",
        "start": 456,
        "end": 457
      },
      {
        "token": "padding",
        "label": "comment",
        "start": 474,
        "end": 481
      },
      {
        "token": ":",
        "label": "comment",
        "start": 481,
        "end": 482
      },
      {
        "token": "5px",
        "label": "comment",
        "start": 483,
        "end": 486
      },
      {
        "token": ";",
        "label": "comment",
        "start": 486,
        "end": 487
      },
      {
        "token": "*",
        "label": "comment",
        "start": 488,
        "end": 489
      },
      {
        "token": "/",
        "label": "comment",
        "start": 489,
        "end": 490
      },
      {
        "token": "2px",
        "label": "extra",
        "start": 515,
        "end": 518
      },
      {
        "token": "/",
        "label": "comment",
        "start": 571,
        "end": 572
      },
      {
        "token": "*",
        "label": "comment",
        "start": 572,
        "end": 573
      },
      {
        "token": "size",
        "label": "comment",
        "start": 574,
        "end": 578
      },
      {
        "token": "includes",
        "label": "comment",
        "start": 579,
        "end": 587
      },
      {
        "token": "padding",
        "label": "comment",
        "start": 588,
        "end": 595
      },
      {
        "token": "and",
        "label": "comment",
        "start": 596,
        "end": 599
      },
      {
        "token": "border",
        "label": "comment",
        "start": 600,
        "end": 606
      },
      {
        "token": "*",
        "label": "comment",
        "start": 607,
        "end": 608
      },
      {
        "token": "/",
        "label": "comment",
        "start": 608,
        "end": 609
      },
      {
        "token": "border",
        "label": "extra",
        "start": 626,
        "end": 632
      },
      {
        "token": "-",
        "label": "extra",
        "start": 632,
        "end": 633
      },
      {
        "token": "radius",
        "label": "extra",
        "start": 633,
        "end": 639
      },
      {
        "token": ":",
        "label": "extra",
        "start": 639,
        "end": 640
      },
      {
        "token": "1px",
        "label": "extra",
        "start": 641,
        "end": 644
      },
      {
        "token": ";",
        "label": "extra",
        "start": 644,
        "end": 645
      },
      {
        "token": "rgb",
        "label": "extra",
        "start": 715,
        "end": 718
      },
      {
        "token": "(",
        "label": "extra",
        "start": 718,
        "end": 719
      },
      {
        "token": "234",
        "label": "extra",
        "start": 719,
        "end": 722
      },
      {
        "token": ",",
        "label": "extra",
        "start": 722,
        "end": 723
      },
      {
        "token": "64",
        "label": "extra",
        "start": 723,
        "end": 725
      },
      {
        "token": ",",
        "label": "extra",
        "start": 725,
        "end": 726
      },
      {
        "token": "12",
        "label": "extra",
        "start": 726,
        "end": 728
      },
      {
        "token": ")",
        "label": "extra",
        "start": 728,
        "end": 729
      },
      {
        "token": "rgb",
        "label": "extra",
        "start": 799,
        "end": 802
      },
      {
        "token": "(",
        "label": "extra",
        "start": 802,
        "end": 803
      },
      {
        "token": "173",
        "label": "extra",
        "start": 803,
        "end": 806
      },
      {
        "token": ",",
        "label": "extra",
        "start": 806,
        "end": 807
      },
      {
        "token": "44",
        "label": "extra",
        "start": 807,
        "end": 809
      },
      {
        "token": ",",
        "label": "extra",
        "start": 809,
        "end": 810
      },
      {
        "token": "5",
        "label": "extra",
        "start": 810,
        "end": 811
      },
      {
        "token": ")",
        "label": "extra",
        "start": 811,
        "end": 812
      },
      {
        "token": ";",
        "label": "extra",
        "start": 812,
        "end": 813
      },
      {
        "token": "}",
        "label": "extra",
        "start": 826,
        "end": 827
      },
      {
        "token": ".",
        "label": "extra",
        "start": 841,
        "end": 842
      },
      {
        "token": "half",
        "label": "extra",
        "start": 842,
        "end": 846
      },
      {
        "token": "-",
        "label": "extra",
        "start": 846,
        "end": 847
      },
      {
        "token": "width",
        "label": "extra",
        "start": 847,
        "end": 852
      },
      {
        "token": "{",
        "label": "extra",
        "start": 853,
        "end": 854
      },
      {
        "token": "width",
        "label": "extra",
        "start": 871,
        "end": 876
      },
      {
        "token": ":",
        "label": "extra",
        "start": 876,
        "end": 877
      },
      {
        "token": "25px",
        "label": "extra",
        "start": 878,
        "end": 882
      },
      {
        "token": "\"",
        "label": "extra",
        "start": 1331,
        "end": 1332
      },
      {
        "token": ">",
        "label": "extra",
        "start": 1332,
        "end": 1333
      },
      {
        "token": "<",
        "label": "extra",
        "start": 1333,
        "end": 1334
      },
      {
        "token": "/",
        "label": "extra",
        "start": 1334,
        "end": 1335
      },
      {
        "token": "div",
        "label": "extra",
        "start": 1335,
        "end": 1338
      },
      {
        "token": ">",
        "label": "extra",
        "start": 1338,
        "end": 1339
      },
      {
        "token": "<",
        "label": "extra",
        "start": 1352,
        "end": 1353
      },
      {
        "token": "div",
        "label": "extra",
        "start": 1353,
        "end": 1356
      },
      {
        "token": "class",
        "label": "extra",
        "start": 1357,
        "end": 1362
      },
      {
        "token": "=",
        "label": "extra",
        "start": 1362,
        "end": 1363
      },
      {
        "token": "\"",
        "label": "extra",
        "start": 1363,
        "end": 1364
      },
      {
        "token": "cell",
        "label": "extra",
        "start": 1364,
        "end": 1368
      },
      {
        "token": "light",
        "label": "extra",
        "start": 1369,
        "end": 1374
      },
      {
        "token": "half",
        "label": "extra",
        "start": 1375,
        "end": 1379
      },
      {
        "token": "-",
        "label": "extra",
        "start": 1379,
        "end": 1380
      },
      {
        "token": "width",
        "label": "extra",
        "start": 1380,
        "end": 1385
      },
      {
        "token": "\"",
        "label": "extra",
        "start": 1385,
        "end": 1386
      },
      {
        "token": ">",
        "label": "extra",
        "start": 1386,
        "end": 1387
      },
      {
        "token": "<",
        "label": "extra",
        "start": 1387,
        "end": 1388
      },
      {
        "token": "/",
        "label": "extra",
        "start": 1388,
        "end": 1389
      },
      {
        "token": "div",
        "label": "extra",
        "start": 1389,
        "end": 1392
      },
      {
        "token": ">",
        "label": "extra",
        "start": 1392,
        "end": 1393
      },
      {
        "token": "<",
        "label": "extra",
        "start": 1407,
        "end": 1408
      },
      {
        "token": "div",
        "label": "extra",
        "start": 1408,
        "end": 1411
      },
      {
        "token": "class",
        "label": "extra",
        "start": 1412,
        "end": 1417
      },
      {
        "token": "=",
        "label": "extra",
        "start": 1417,
        "end": 1418
      },
      {
        "token": "\"",
        "label": "extra",
        "start": 1418,
        "end": 1419
      },
      {
        "token": "cell",
        "label": "extra",
        "start": 1419,
        "end": 1423
      },
      {
        "token": "light",
        "label": "extra",
        "start": 1424,
        "end": 1429
      },
      {
        "token": "half",
        "label": "extra",
        "start": 1430,
        "end": 1434
      },
      {
        "token": "-",
        "label": "extra",
        "start": 1434,
        "end": 1435
      },
      {
        "token": "width",
        "label": "extra",
        "start": 1435,
        "end": 1440
      },
      {
        "token": "light",
        "label": "extra",
        "start": 2171,
        "end": 2176
      },
      {
        "token": "half",
        "label": "extra",
        "start": 2177,
        "end": 2181
      },
      {
        "token": "-",
        "label": "extra",
        "start": 2181,
        "end": 2182
      },
      {
        "token": "width",
        "label": "extra",
        "start": 2182,
        "end": 2187
      },
      {
        "token": "half",
        "label": "extra",
        "start": 2232,
        "end": 2236
      },
      {
        "token": "-",
        "label": "extra",
        "start": 2236,
        "end": 2237
      },
      {
        "token": "width",
        "label": "extra",
        "start": 2237,
        "end": 2242
      },
      {
        "token": "light",
        "label": "extra",
        "start": 2973,
        "end": 2978
      },
      {
        "token": "half",
        "label": "extra",
        "start": 2979,
        "end": 2983
      },
      {
        "token": "-",
        "label": "extra",
        "start": 2983,
        "end": 2984
      },
      {
        "token": "width",
        "label": "extra",
        "start": 2984,
        "end": 2989
      },
      {
        "token": "\"",
        "label": "extra",
        "start": 2989,
        "end": 2990
      },
      {
        "token": ">",
        "label": "extra",
        "start": 2990,
        "end": 2991
      },
      {
        "token": "<",
        "label": "extra",
        "start": 2991,
        "end": 2992
      },
      {
        "token": "/",
        "label": "extra",
        "start": 2992,
        "end": 2993
      },
      {
        "token": "div",
        "label": "extra",
        "start": 2993,
        "end": 2996
      },
      {
        "token": ">",
        "label": "extra",
        "start": 2996,
        "end": 2997
      },
      {
        "token": "<",
        "label": "extra",
        "start": 3011,
        "end": 3012
      },
      {
        "token": "div",
        "label": "extra",
        "start": 3012,
        "end": 3015
      },
      {
        "token": "class",
        "label": "extra",
        "start": 3016,
        "end": 3021
      },
      {
        "token": "=",
        "label": "extra",
        "start": 3021,
        "end": 3022
      },
      {
        "token": "\"",
        "label": "extra",
        "start": 3022,
        "end": 3023
      },
      {
        "token": "cell",
        "label": "extra",
        "start": 3023,
        "end": 3027
      },
      {
        "token": "light",
        "label": "extra",
        "start": 3028,
        "end": 3033
      },
      {
        "token": "half",
        "label": "extra",
        "start": 3034,
        "end": 3038
      },
      {
        "token": "-",
        "label": "extra",
        "start": 3038,
        "end": 3039
      },
      {
        "token": "width",
        "label": "extra",
        "start": 3039,
        "end": 3044
      },
      {
        "token": "\"",
        "label": "extra",
        "start": 3044,
        "end": 3045
      },
      {
        "token": ">",
        "label": "extra",
        "start": 3045,
        "end": 3046
      },
      {
        "token": "<",
        "label": "extra",
        "start": 3046,
        "end": 3047
      },
      {
        "token": "/",
        "label": "extra",
        "start": 3047,
        "end": 3048
      },
      {
        "token": "div",
        "label": "extra",
        "start": 3048,
        "end": 3051
      },
      {
        "token": ">",
        "label": "extra",
        "start": 3051,
        "end": 3052
      },
      {
        "token": "<",
        "label": "extra",
        "start": 3065,
        "end": 3066
      },
      {
        "token": "div",
        "label": "extra",
        "start": 3066,
        "end": 3069
      },
      {
        "token": "class",
        "label": "extra",
        "start": 3070,
        "end": 3075
      },
      {
        "token": "=",
        "label": "extra",
        "start": 3075,
        "end": 3076
      },
      {
        "token": "\"",
        "label": "extra",
        "start": 3076,
        "end": 3077
      },
      {
        "token": "cell",
        "label": "extra",
        "start": 3077,
        "end": 3081
      },
      {
        "token": "dark",
        "label": "extra",
        "start": 3082,
        "end": 3086
      },
      {
        "token": "\"",
        "label": "extra",
        "start": 3086,
        "end": 3087
      },
      {
        "token": ">",
        "label": "extra",
        "start": 3087,
        "end": 3088
      },
      {
        "token": "<",
        "label": "extra",
        "start": 3088,
        "end": 3089
      },
      {
        "token": "/",
        "label": "extra",
        "start": 3089,
        "end": 3090
      },
      {
        "token": "div",
        "label": "extra",
        "start": 3090,
        "end": 3093
      },
      {
        "token": ">",
        "label": "extra",
        "start": 3093,
        "end": 3094
      },
      {
        "token": "<",
        "label": "extra",
        "start": 3107,
        "end": 3108
      },
      {
        "token": "div",
        "label": "extra",
        "start": 3108,
        "end": 3111
      },
      {
        "token": "class",
        "label": "extra",
        "start": 3112,
        "end": 3117
      },
      {
        "token": "=",
        "label": "extra",
        "start": 3117,
        "end": 3118
      },
      {
        "token": "\"",
        "label": "extra",
        "start": 3118,
        "end": 3119
      },
      {
        "token": "cell",
        "label": "extra",
        "start": 3119,
        "end": 3123
      },
      {
        "token": "light",
        "label": "extra",
        "start": 3124,
        "end": 3129
      },
      {
        "token": "\"",
        "label": "extra",
        "start": 3129,
        "end": 3130
      },
      {
        "token": ">",
        "label": "extra",
        "start": 3130,
        "end": 3131
      },
      {
        "token": "<",
        "label": "extra",
        "start": 3131,
        "end": 3132
      },
      {
        "token": "/",
        "label": "extra",
        "start": 3132,
        "end": 3133
      },
      {
        "token": "div",
        "label": "extra",
        "start": 3133,
        "end": 3136
      },
      {
        "token": ">",
        "label": "extra",
        "start": 3136,
        "end": 3137
      },
      {
        "token": "<",
        "label": "extra",
        "start": 3150,
        "end": 3151
      },
      {
        "token": "div",
        "label": "extra",
        "start": 3151,
        "end": 3154
      },
      {
        "token": "class",
        "label": "extra",
        "start": 3155,
        "end": 3160
      },
      {
        "token": "=",
        "label": "extra",
        "start": 3160,
        "end": 3161
      },
      {
        "token": "\"",
        "label": "extra",
        "start": 3161,
        "end": 3162
      },
      {
        "token": "cell",
        "label": "extra",
        "start": 3162,
        "end": 3166
      },
      {
        "token": "dark",
        "label": "extra",
        "start": 3167,
        "end": 3171
      },
      {
        "token": "\"",
        "label": "extra",
        "start": 3171,
        "end": 3172
      },
      {
        "token": ">",
        "label": "extra",
        "start": 3172,
        "end": 3173
      },
      {
        "token": "<",
        "label": "extra",
        "start": 3173,
        "end": 3174
      },
      {
        "token": "/",
        "label": "extra",
        "start": 3174,
        "end": 3175
      },
      {
        "token": "div",
        "label": "extra",
        "start": 3175,
        "end": 3178
      },
      {
        "token": ">",
        "label": "extra",
        "start": 3178,
        "end": 3179
      },
      {
        "token": "<",
        "label": "extra",
        "start": 3192,
        "end": 3193
      },
      {
        "token": "div",
        "label": "extra",
        "start": 3193,
        "end": 3196
      },
      {
        "token": "class",
        "label": "extra",
        "start": 3197,
        "end": 3202
      },
      {
        "token": "=",
        "label": "extra",
        "start": 3202,
        "end": 3203
      },
      {
        "token": "\"",
        "label": "extra",
        "start": 3203,
        "end": 3204
      },
      {
        "token": "cell",
        "label": "extra",
        "start": 3204,
        "end": 3208
      },
      {
        "token": "light",
        "label": "extra",
        "start": 3209,
        "end": 3214
      },
      {
        "token": "\"",
        "label": "extra",
        "start": 3214,
        "end": 3215
      },
      {
        "token": ">",
        "label": "extra",
        "start": 3215,
        "end": 3216
      },
      {
        "token": "<",
        "label": "extra",
        "start": 3216,
        "end": 3217
      },
      {
        "token": "/",
        "label": "extra",
        "start": 3217,
        "end": 3218
      },
      {
        "token": "div",
        "label": "extra",
        "start": 3218,
        "end": 3221
      },
      {
        "token": ">",
        "label": "extra",
        "start": 3221,
        "end": 3222
      },
      {
        "token": "<",
        "label": "extra",
        "start": 3235,
        "end": 3236
      },
      {
        "token": "div",
        "label": "extra",
        "start": 3236,
        "end": 3239
      },
      {
        "token": "class",
        "label": "extra",
        "start": 3240,
        "end": 3245
      },
      {
        "token": "=",
        "label": "extra",
        "start": 3245,
        "end": 3246
      },
      {
        "token": "\"",
        "label": "extra",
        "start": 3246,
        "end": 3247
      },
      {
        "token": "cell",
        "label": "extra",
        "start": 3247,
        "end": 3251
      },
      {
        "token": "dark",
        "label": "extra",
        "start": 3252,
        "end": 3256
      },
      {
        "token": "\"",
        "label": "extra",
        "start": 3256,
        "end": 3257
      },
      {
        "token": ">",
        "label": "extra",
        "start": 3257,
        "end": 3258
      },
      {
        "token": "<",
        "label": "extra",
        "start": 3258,
        "end": 3259
      },
      {
        "token": "/",
        "label": "extra",
        "start": 3259,
        "end": 3260
      },
      {
        "token": "div",
        "label": "extra",
        "start": 3260,
        "end": 3263
      },
      {
        "token": ">",
        "label": "extra",
        "start": 3263,
        "end": 3264
      },
      {
        "token": "<",
        "label": "extra",
        "start": 3277,
        "end": 3278
      },
      {
        "token": "div",
        "label": "extra",
        "start": 3278,
        "end": 3281
      },
      {
        "token": "class",
        "label": "extra",
        "start": 3282,
        "end": 3287
      },
      {
        "token": "=",
        "label": "extra",
        "start": 3287,
        "end": 3288
      },
      {
        "token": "\"",
        "label": "extra",
        "start": 3288,
        "end": 3289
      },
      {
        "token": "cell",
        "label": "extra",
        "start": 3289,
        "end": 3293
      },
      {
        "token": "light",
        "label": "extra",
        "start": 3294,
        "end": 3299
      },
      {
        "token": "\"",
        "label": "extra",
        "start": 3299,
        "end": 3300
      },
      {
        "token": ">",
        "label": "extra",
        "start": 3300,
        "end": 3301
      },
      {
        "token": "<",
        "label": "extra",
        "start": 3301,
        "end": 3302
      },
      {
        "token": "/",
        "label": "extra",
        "start": 3302,
        "end": 3303
      },
      {
        "token": "div",
        "label": "extra",
        "start": 3303,
        "end": 3306
      },
      {
        "token": ">",
        "label": "extra",
        "start": 3306,
        "end": 3307
      },
      {
        "token": "<",
        "label": "extra",
        "start": 3320,
        "end": 3321
      },
      {
        "token": "div",
        "label": "extra",
        "start": 3321,
        "end": 3324
      },
      {
        "token": "class",
        "label": "extra",
        "start": 3325,
        "end": 3330
      },
      {
        "token": "=",
        "label": "extra",
        "start": 3330,
        "end": 3331
      },
      {
        "token": "\"",
        "label": "extra",
        "start": 3331,
        "end": 3332
      },
      {
        "token": "cell",
        "label": "extra",
        "start": 3332,
        "end": 3336
      },
      {
        "token": "dark",
        "label": "extra",
        "start": 3337,
        "end": 3341
      },
      {
        "token": "\"",
        "label": "extra",
        "start": 3341,
        "end": 3342
      },
      {
        "token": ">",
        "label": "extra",
        "start": 3342,
        "end": 3343
      },
      {
        "token": "<",
        "label": "extra",
        "start": 3343,
        "end": 3344
      },
      {
        "token": "/",
        "label": "extra",
        "start": 3344,
        "end": 3345
      },
      {
        "token": "div",
        "label": "extra",
        "start": 3345,
        "end": 3348
      },
      {
        "token": ">",
        "label": "extra",
        "start": 3348,
        "end": 3349
      },
      {
        "token": "<",
        "label": "extra",
        "start": 3362,
        "end": 3363
      },
      {
        "token": "div",
        "label": "extra",
        "start": 3363,
        "end": 3366
      },
      {
        "token": "class",
        "label": "extra",
        "start": 3367,
        "end": 3372
      },
      {
        "token": "=",
        "label": "extra",
        "start": 3372,
        "end": 3373
      },
      {
        "token": "\"",
        "label": "extra",
        "start": 3373,
        "end": 3374
      },
      {
        "token": "cell",
        "label": "extra",
        "start": 3374,
        "end": 3378
      },
      {
        "token": "light",
        "label": "extra",
        "start": 3379,
        "end": 3384
      },
      {
        "token": "\"",
        "label": "extra",
        "start": 3384,
        "end": 3385
      },
      {
        "token": ">",
        "label": "extra",
        "start": 3385,
        "end": 3386
      },
      {
        "token": "<",
        "label": "extra",
        "start": 3386,
        "end": 3387
      },
      {
        "token": "/",
        "label": "extra",
        "start": 3387,
        "end": 3388
      },
      {
        "token": "div",
        "label": "extra",
        "start": 3388,
        "end": 3391
      },
      {
        "token": ">",
        "label": "extra",
        "start": 3391,
        "end": 3392
      },
      {
        "token": "<",
        "label": "extra",
        "start": 3418,
        "end": 3419
      },
      {
        "token": "div",
        "label": "extra",
        "start": 3419,
        "end": 3422
      },
      {
        "token": "class",
        "label": "extra",
        "start": 3423,
        "end": 3428
      },
      {
        "token": "=",
        "label": "extra",
        "start": 3428,
        "end": 3429
      },
      {
        "token": "\"",
        "label": "extra",
        "start": 3429,
        "end": 3430
      },
      {
        "token": "cell",
        "label": "extra",
        "start": 3430,
        "end": 3434
      },
      {
        "token": "light",
        "label": "extra",
        "start": 3435,
        "end": 3440
      },
      {
        "token": "\"",
        "label": "extra",
        "start": 3440,
        "end": 3441
      },
      {
        "token": ">",
        "label": "extra",
        "start": 3441,
        "end": 3442
      },
      {
        "token": "<",
        "label": "extra",
        "start": 3442,
        "end": 3443
      },
      {
        "token": "/",
        "label": "extra",
        "start": 3443,
        "end": 3444
      },
      {
        "token": "div",
        "label": "extra",
        "start": 3444,
        "end": 3447
      },
      {
        "token": ">",
        "label": "extra",
        "start": 3447,
        "end": 3448
      },
      {
        "token": "<",
        "label": "extra",
        "start": 3461,
        "end": 3462
      },
      {
        "token": "div",
        "label": "extra",
        "start": 3462,
        "end": 3465
      },
      {
        "token": "class",
        "label": "extra",
        "start": 3466,
        "end": 3471
      },
      {
        "token": "=",
        "label": "extra",
        "start": 3471,
        "end": 3472
      },
      {
        "token": "\"",
        "label": "extra",
        "start": 3472,
        "end": 3473
      },
      {
        "token": "cell",
        "label": "extra",
        "start": 3473,
        "end": 3477
      },
      {
        "token": "dark",
        "label": "extra",
        "start": 3478,
        "end": 3482
      },
      {
        "token": "\"",
        "label": "extra",
        "start": 3482,
        "end": 3483
      },
      {
        "token": ">",
        "label": "extra",
        "start": 3483,
        "end": 3484
      },
      {
        "token": "<",
        "label": "extra",
        "start": 3484,
        "end": 3485
      },
      {
        "token": "/",
        "label": "extra",
        "start": 3485,
        "end": 3486
      },
      {
        "token": "div",
        "label": "extra",
        "start": 3486,
        "end": 3489
      },
      {
        "token": ">",
        "label": "extra",
        "start": 3489,
        "end": 3490
      },
      {
        "token": "<",
        "label": "extra",
        "start": 3503,
        "end": 3504
      },
      {
        "token": "div",
        "label": "extra",
        "start": 3504,
        "end": 3507
      },
      {
        "token": "class",
        "label": "extra",
        "start": 3508,
        "end": 3513
      },
      {
        "token": "=",
        "label": "extra",
        "start": 3513,
        "end": 3514
      },
      {
        "token": "\"",
        "label": "extra",
        "start": 3514,
        "end": 3515
      },
      {
        "token": "cell",
        "label": "extra",
        "start": 3515,
        "end": 3519
      },
      {
        "token": "light",
        "label": "extra",
        "start": 3520,
        "end": 3525
      },
      {
        "token": "\"",
        "label": "extra",
        "start": 3525,
        "end": 3526
      },
      {
        "token": ">",
        "label": "extra",
        "start": 3526,
        "end": 3527
      },
      {
        "token": "<",
        "label": "extra",
        "start": 3527,
        "end": 3528
      },
      {
        "token": "/",
        "label": "extra",
        "start": 3528,
        "end": 3529
      },
      {
        "token": "div",
        "label": "extra",
        "start": 3529,
        "end": 3532
      },
      {
        "token": ">",
        "label": "extra",
        "start": 3532,
        "end": 3533
      },
      {
        "token": "<",
        "label": "extra",
        "start": 3546,
        "end": 3547
      },
      {
        "token": "div",
        "label": "extra",
        "start": 3547,
        "end": 3550
      },
      {
        "token": "class",
        "label": "extra",
        "start": 3551,
        "end": 3556
      },
      {
        "token": "=",
        "label": "extra",
        "start": 3556,
        "end": 3557
      },
      {
        "token": "\"",
        "label": "extra",
        "start": 3557,
        "end": 3558
      },
      {
        "token": "cell",
        "label": "extra",
        "start": 3558,
        "end": 3562
      },
      {
        "token": "dark",
        "label": "extra",
        "start": 3563,
        "end": 3567
      },
      {
        "token": "\"",
        "label": "extra",
        "start": 3567,
        "end": 3568
      },
      {
        "token": ">",
        "label": "extra",
        "start": 3568,
        "end": 3569
      },
      {
        "token": "<",
        "label": "extra",
        "start": 3569,
        "end": 3570
      },
      {
        "token": "/",
        "label": "extra",
        "start": 3570,
        "end": 3571
      },
      {
        "token": "div",
        "label": "extra",
        "start": 3571,
        "end": 3574
      },
      {
        "token": ">",
        "label": "extra",
        "start": 3574,
        "end": 3575
      },
      {
        "token": "<",
        "label": "extra",
        "start": 3588,
        "end": 3589
      },
      {
        "token": "div",
        "label": "extra",
        "start": 3589,
        "end": 3592
      },
      {
        "token": "class",
        "label": "extra",
        "start": 3593,
        "end": 3598
      },
      {
        "token": "=",
        "label": "extra",
        "start": 3598,
        "end": 3599
      },
      {
        "token": "\"",
        "label": "extra",
        "start": 3599,
        "end": 3600
      },
      {
        "token": "cell",
        "label": "extra",
        "start": 3600,
        "end": 3604
      },
      {
        "token": "light",
        "label": "extra",
        "start": 3605,
        "end": 3610
      },
      {
        "token": "\"",
        "label": "extra",
        "start": 3610,
        "end": 3611
      },
      {
        "token": ">",
        "label": "extra",
        "start": 3611,
        "end": 3612
      },
      {
        "token": "<",
        "label": "extra",
        "start": 3612,
        "end": 3613
      },
      {
        "token": "/",
        "label": "extra",
        "start": 3613,
        "end": 3614
      },
      {
        "token": "div",
        "label": "extra",
        "start": 3614,
        "end": 3617
      },
      {
        "token": ">",
        "label": "extra",
        "start": 3617,
        "end": 3618
      },
      {
        "token": "<",
        "label": "extra",
        "start": 3631,
        "end": 3632
      },
      {
        "token": "div",
        "label": "extra",
        "start": 3632,
        "end": 3635
      },
      {
        "token": "class",
        "label": "extra",
        "start": 3636,
        "end": 3641
      },
      {
        "token": "=",
        "label": "extra",
        "start": 3641,
        "end": 3642
      },
      {
        "token": "\"",
        "label": "extra",
        "start": 3642,
        "end": 3643
      },
      {
        "token": "cell",
        "label": "extra",
        "start": 3643,
        "end": 3647
      },
      {
        "token": "dark",
        "label": "extra",
        "start": 3648,
        "end": 3652
      },
      {
        "token": "\"",
        "label": "extra",
        "start": 3652,
        "end": 3653
      },
      {
        "token": ">",
        "label": "extra",
        "start": 3653,
        "end": 3654
      },
      {
        "token": "<",
        "label": "extra",
        "start": 3654,
        "end": 3655
      },
      {
        "token": "/",
        "label": "extra",
        "start": 3655,
        "end": 3656
      },
      {
        "token": "div",
        "label": "extra",
        "start": 3656,
        "end": 3659
      },
      {
        "token": ">",
        "label": "extra",
        "start": 3659,
        "end": 3660
      },
      {
        "token": "<",
        "label": "extra",
        "start": 3673,
        "end": 3674
      },
      {
        "token": "div",
        "label": "extra",
        "start": 3674,
        "end": 3677
      },
      {
        "token": "class",
        "label": "extra",
        "start": 3678,
        "end": 3683
      },
      {
        "token": "=",
        "label": "extra",
        "start": 3683,
        "end": 3684
      },
      {
        "token": "\"",
        "label": "extra",
        "start": 3684,
        "end": 3685
      },
      {
        "token": "cell",
        "label": "extra",
        "start": 3685,
        "end": 3689
      },
      {
        "token": "light",
        "label": "extra",
        "start": 3690,
        "end": 3695
      },
      {
        "token": "\"",
        "label": "extra",
        "start": 3695,
        "end": 3696
      },
      {
        "token": ">",
        "label": "extra",
        "start": 3696,
        "end": 3697
      },
      {
        "token": "<",
        "label": "extra",
        "start": 3697,
        "end": 3698
      },
      {
        "token": "/",
        "label": "extra",
        "start": 3698,
        "end": 3699
      },
      {
        "token": "div",
        "label": "extra",
        "start": 3699,
        "end": 3702
      },
      {
        "token": ">",
        "label": "extra",
        "start": 3702,
        "end": 3703
      },
      {
        "token": "<",
        "label": "extra",
        "start": 3716,
        "end": 3717
      },
      {
        "token": "div",
        "label": "extra",
        "start": 3717,
        "end": 3720
      },
      {
        "token": "class",
        "label": "extra",
        "start": 3721,
        "end": 3726
      },
      {
        "token": "=",
        "label": "extra",
        "start": 3726,
        "end": 3727
      },
      {
        "token": "\"",
        "label": "extra",
        "start": 3727,
        "end": 3728
      },
      {
        "token": "cell",
        "label": "extra",
        "start": 3728,
        "end": 3732
      },
      {
        "token": "dark",
        "label": "extra",
        "start": 3733,
        "end": 3737
      },
      {
        "token": "\"",
        "label": "extra",
        "start": 3737,
        "end": 3738
      },
      {
        "token": ">",
        "label": "extra",
        "start": 3738,
        "end": 3739
      },
      {
        "token": "<",
        "label": "extra",
        "start": 3739,
        "end": 3740
      },
      {
        "token": "/",
        "label": "extra",
        "start": 3740,
        "end": 3741
      },
      {
        "token": "div",
        "label": "extra",
        "start": 3741,
        "end": 3744
      },
      {
        "token": ">",
        "label": "extra",
        "start": 3744,
        "end": 3745
      },
      {
        "token": "<",
        "label": "extra",
        "start": 3758,
        "end": 3759
      },
      {
        "token": "div",
        "label": "extra",
        "start": 3759,
        "end": 3762
      },
      {
        "token": "class",
        "label": "extra",
        "start": 3763,
        "end": 3768
      },
      {
        "token": "=",
        "label": "extra",
        "start": 3768,
        "end": 3769
      },
      {
        "token": "\"",
        "label": "extra",
        "start": 3769,
        "end": 3770
      },
      {
        "token": "cell",
        "label": "extra",
        "start": 3770,
        "end": 3774
      },
      {
        "token": "light",
        "label": "extra",
        "start": 3775,
        "end": 3780
      },
      {
        "token": "half",
        "label": "extra",
        "start": 3781,
        "end": 3785
      },
      {
        "token": "-",
        "label": "extra",
        "start": 3785,
        "end": 3786
      },
      {
        "token": "width",
        "label": "extra",
        "start": 3786,
        "end": 3791
      },
      {
        "token": "\"",
        "label": "extra",
        "start": 3791,
        "end": 3792
      },
      {
        "token": ">",
        "label": "extra",
        "start": 3792,
        "end": 3793
      },
      {
        "token": "<",
        "label": "extra",
        "start": 3793,
        "end": 3794
      },
      {
        "token": "/",
        "label": "extra",
        "start": 3794,
        "end": 3795
      },
      {
        "token": "div",
        "label": "extra",
        "start": 3795,
        "end": 3798
      },
      {
        "token": ">",
        "label": "extra",
        "start": 3798,
        "end": 3799
      },
      {
        "token": "<",
        "label": "extra",
        "start": 3813,
        "end": 3814
      },
      {
        "token": "div",
        "label": "extra",
        "start": 3814,
        "end": 3817
      },
      {
        "token": "class",
        "label": "extra",
        "start": 3818,
        "end": 3823
      },
      {
        "token": "=",
        "label": "extra",
        "start": 3823,
        "end": 3824
      },
      {
        "token": "\"",
        "label": "extra",
        "start": 3824,
        "end": 3825
      },
      {
        "token": "cell",
        "label": "extra",
        "start": 3825,
        "end": 3829
      },
      {
        "token": "light",
        "label": "extra",
        "start": 3830,
        "end": 3835
      },
      {
        "token": "half",
        "label": "extra",
        "start": 3836,
        "end": 3840
      },
      {
        "token": "-",
        "label": "extra",
        "start": 3840,
        "end": 3841
      },
      {
        "token": "width",
        "label": "extra",
        "start": 3841,
        "end": 3846
      },
      {
        "token": "\"",
        "label": "extra",
        "start": 3846,
        "end": 3847
      },
      {
        "token": ">",
        "label": "extra",
        "start": 3847,
        "end": 3848
      },
      {
        "token": "<",
        "label": "extra",
        "start": 3848,
        "end": 3849
      },
      {
        "token": "/",
        "label": "extra",
        "start": 3849,
        "end": 3850
      },
      {
        "token": "div",
        "label": "extra",
        "start": 3850,
        "end": 3853
      },
      {
        "token": ">",
        "label": "extra",
        "start": 3853,
        "end": 3854
      },
      {
        "token": "<",
        "label": "extra",
        "start": 3867,
        "end": 3868
      },
      {
        "token": "div",
        "label": "extra",
        "start": 3868,
        "end": 3871
      },
      {
        "token": "class",
        "label": "extra",
        "start": 3872,
        "end": 3877
      },
      {
        "token": "=",
        "label": "extra",
        "start": 3877,
        "end": 3878
      },
      {
        "token": "\"",
        "label": "extra",
        "start": 3878,
        "end": 3879
      },
      {
        "token": "cell",
        "label": "extra",
        "start": 3879,
        "end": 3883
      },
      {
        "token": "<",
        "label": "comment",
        "start": 4219,
        "end": 4220
      },
      {
        "token": "!",
        "label": "comment",
        "start": 4220,
        "end": 4221
      },
      {
        "token": "-",
        "label": "comment",
        "start": 4221,
        "end": 4222
      },
      {
        "token": "-",
        "label": "comment",
        "start": 4222,
        "end": 4223
      },
      {
        "token": "div",
        "label": "comment",
        "start": 4224,
        "end": 4227
      },
      {
        "token": "with",
        "label": "comment",
        "start": 4228,
        "end": 4232
      },
      {
        "token": "Inline",
        "label": "comment",
        "start": 4233,
        "end": 4239
      },
      {
        "token": "Style",
        "label": "comment",
        "start": 4240,
        "end": 4245
      },
      {
        "token": "(",
        "label": "comment",
        "start": 4246,
        "end": 4247
      },
      {
        "token": "not",
        "label": "comment",
        "start": 4247,
        "end": 4250
      },
      {
        "token": "recommended",
        "label": "comment",
        "start": 4251,
        "end": 4262
      },
      {
        "token": ")",
        "label": "comment",
        "start": 4262,
        "end": 4263
      },
      {
        "token": "<",
        "label": "comment",
        "start": 4273,
        "end": 4274
      },
      {
        "token": "div",
        "label": "comment",
        "start": 4274,
        "end": 4277
      },
      {
        "token": "style",
        "label": "comment",
        "start": 4278,
        "end": 4283
      },
      {
        "token": "=",
        "label": "comment",
        "start": 4283,
        "end": 4284
      },
      {
        "token": "\"",
        "label": "comment",
        "start": 4284,
        "end": 4285
      },
      {
        "token": "height",
        "label": "comment",
        "start": 4298,
        "end": 4304
      },
      {
        "token": ":",
        "label": "comment",
        "start": 4304,
        "end": 4305
      },
      {
        "token": "50px",
        "label": "comment",
        "start": 4306,
        "end": 4310
      },
      {
        "token": ";",
        "label": "comment",
        "start": 4310,
        "end": 4311
      },
      {
        "token": "background",
        "label": "comment",
        "start": 4324,
        "end": 4334
      },
      {
        "token": "-",
        "label": "comment",
        "start": 4334,
        "end": 4335
      },
      {
        "token": "color",
        "label": "comment",
        "start": 4335,
        "end": 4340
      },
      {
        "token": ":",
        "label": "comment",
        "start": 4340,
        "end": 4341
      },
      {
        "token": "black",
        "label": "comment",
        "start": 4342,
        "end": 4347
      },
      {
        "token": ";",
        "label": "comment",
        "start": 4347,
        "end": 4348
      },
      {
        "token": "width",
        "label": "comment",
        "start": 4361,
        "end": 4366
      },
      {
        "token": ":",
        "label": "comment",
        "start": 4366,
        "end": 4367
      },
      {
        "token": "50px",
        "label": "comment",
        "start": 4368,
        "end": 4372
      },
      {
        "token": ";",
        "label": "comment",
        "start": 4372,
        "end": 4373
      },
      {
        "token": "\"",
        "label": "comment",
        "start": 4382,
        "end": 4383
      },
      {
        "token": ">",
        "label": "comment",
        "start": 4383,
        "end": 4384
      },
      {
        "token": "<",
        "label": "comment",
        "start": 4384,
        "end": 4385
      },
      {
        "token": "/",
        "label": "comment",
        "start": 4385,
        "end": 4386
      },
      {
        "token": "div",
        "label": "comment",
        "start": 4386,
        "end": 4389
      },
      {
        "token": ">",
        "label": "comment",
        "start": 4389,
        "end": 4390
      },
      {
        "token": "-",
        "label": "comment",
        "start": 4391,
        "end": 4392
      },
      {
        "token": "-",
        "label": "comment",
        "start": 4392,
        "end": 4393
      },
      {
        "token": ">",
        "label": "comment",
        "start": 4393,
        "end": 4394
      }
    ]
  }
}